{"title": "ww2", "platform": "ps4", "id": "ba5070d2-a583-5841-8c1b-23dfd8c37889", "series_id": "pool-A-5", "start_time_s": 1515803162, "end_time_s": 1515803692, "duration_ms": 530000, "mode": "Hardpoint", "map": "Ardennes Forest", "rounds": 1, "hp_hill_names": ["cave", "ruins", "bunker", "road"], "hp_hill_rotations": 9, "teams": [{"name": "MINDFREAK", "score": 121, "is_victor": false, "round_scores": [9, 9, 9, 35, 27, 0, 10, 22, 0], "side": "home"}, {"name": "FAZE CLAN", "score": 250, "is_victor": true, "round_scores": [26, 40, 32, 15, 17, 54, 23, 15, 28], "side": "away"}], "players": [{"name": "BUZZO", "team": "MINDFREAK", "kills": 12, "deaths": 23, "kd": 0.52, "kills_per_10min": 13.6, "deaths_per_10min": 26.0, "assists": 10, "headshots": 1, "suicides": 0, "team_kills": 1, "team_deaths": 0, "stayed_alive_kills": 5, "hits": 56, "shots": 177, "accuracy": 31.6, "num_lives": 24, "time_alive_s": 479.8, "avg_time_per_life_s": 20.0, "fave_weapon": "BAR", "fave_division": "Infantry", "fave_training": "Hunker", "fave_scorestreaks": ["Fighter Pilot", "Glide Bomb", "Mortar Strike"], "2piece": 1, "3piece": 0, "4piece": 0, "4streak": 0, "5streak": 0, "6streak": 0, "7streak": 0, "8+streak": 0, "scorestreaks_earned": 0, "scorestreaks_used": 0, "scorestreaks_deployed": 0, "scorestreaks_kills": 0, "scorestreaks_assists": 0, "hp_hill_time_s": 16, "hp_captures": 0, "hp_defends": 1}, {"name": "DENZ", "team": "MINDFREAK", "kills": 27, "deaths": 22, "kd": 1.23, "kills_per_10min": 30.6, "deaths_per_10min": 24.9, "assists": 7, "headshots": 3, "suicides": 0, "team_kills": 0, "team_deaths": 0, "stayed_alive_kills": 19, "hits": 111, "shots": 379, "accuracy": 29.3, "num_lives": 23, "time_alive_s": 483.9, "avg_time_per_life_s": 21.0, "fave_weapon": "STG-44", "fave_division": "Infantry", "fave_training": "Hunker", "fave_scorestreaks": ["Fighter Pilot", "Glide Bomb", "Flamethrower"], "2piece": 4, "3piece": 0, "4piece": 0, "4streak": 2, "5streak": 0, "6streak": 0, "7streak": 0, "8+streak": 0, "scorestreaks_earned": 0, "scorestreaks_used": 0, "scorestreaks_deployed": 0, "scorestreaks_kills": 0, "scorestreaks_assists": 0, "hp_hill_time_s": 28, "hp_captures": 0, "hp_defends": 1}, {"name": "FIGHTA", "team": "MINDFREAK", "kills": 18, "deaths": 27, "kd": 0.67, "kills_per_10min": 20.4, "deaths_per_10min": 30.6, "assists": 8, "headshots": 2, "suicides": 0, "team_kills": 0, "team_deaths": 1, "stayed_alive_kills": 14, "hits": 84, "shots": 314, "accuracy": 26.8, "num_lives": 29, "time_alive_s": 473.3, "avg_time_per_life_s": 16.3, "fave_weapon": "PPSh-41", "fave_division": "Airborne", "fave_training": "Hunker", "fave_scorestreaks": ["Fighter Pilot", "Glide Bomb", "Mortar Strike"], "2piece": 1, "3piece": 0, "4piece": 0, "4streak": 0, "5streak": 0, "6streak": 0, "7streak": 0, "8+streak": 0, "scorestreaks_earned": 0, "scorestreaks_used": 0, "scorestreaks_deployed": 0, "scorestreaks_kills": 0, "scorestreaks_assists": 0, "hp_hill_time_s": 72, "hp_captures": 0, "hp_defends": 1}, {"name": "SHOCKZ", "team": "MINDFREAK", "kills": 25, "deaths": 28, "kd": 0.89, "kills_per_10min": 28.3, "deaths_per_10min": 31.7, "assists": 10, "headshots": 3, "suicides": 0, "team_kills": 0, "team_deaths": 0, "stayed_alive_kills": 17, "hits": 108, "shots": 369, "accuracy": 29.3, "num_lives": 29, "time_alive_s": 473.4, "avg_time_per_life_s": 16.3, "fave_weapon": "PPSh-41", "fave_division": "Airborne", "fave_training": "Hunker", "fave_scorestreaks": ["Fighter Pilot", "Glide Bomb", "Mortar Strike"], "2piece": 3, "3piece": 1, "4piece": 0, "4streak": 0, "5streak": 0, "6streak": 0, "7streak": 0, "8+streak": 0, "scorestreaks_earned": 0, "scorestreaks_used": 0, "scorestreaks_deployed": 0, "scorestreaks_kills": 0, "scorestreaks_assists": 0, "hp_hill_time_s": 14, "hp_captures": 0, "hp_defends": 0}, {"name": "ATTACH", "team": "FAZE CLAN", "kills": 20, "deaths": 21, "kd": 0.95, "kills_per_10min": 22.6, "deaths_per_10min": 23.8, "assists": 9, "headshots": 0, "suicides": 0, "team_kills": 1, "team_deaths": 0, "stayed_alive_kills": 14, "hits": 79, "shots": 328, "accuracy": 24.1, "num_lives": 22, "time_alive_s": 487.6, "avg_time_per_life_s": 22.2, "fave_weapon": "PPSh-41", "fave_division": "Airborne", "fave_training": "Hunker", "fave_scorestreaks": ["Fighter Pilot", "Glide Bomb", "Artillery Barrage"], "2piece": 3, "3piece": 0, "4piece": 0, "4streak": 0, "5streak": 0, "6streak": 0, "7streak": 1, "8+streak": 0, "scorestreaks_earned": 3, "scorestreaks_used": 3, "scorestreaks_deployed": 3, "scorestreaks_kills": 5, "scorestreaks_assists": 0, "hp_hill_time_s": 46, "hp_captures": 0, "hp_defends": 0}, {"name": "PRIESTAH", "team": "FAZE CLAN", "kills": 26, "deaths": 19, "kd": 1.37, "kills_per_10min": 29.4, "deaths_per_10min": 21.5, "assists": 8, "headshots": 0, "suicides": 0, "team_kills": 0, "team_deaths": 1, "stayed_alive_kills": 17, "hits": 91, "shots": 310, "accuracy": 29.4, "num_lives": 21, "time_alive_s": 489.1, "avg_time_per_life_s": 23.3, "fave_weapon": "STG-44", "fave_division": "Infantry", "fave_training": "Hunker", "fave_scorestreaks": ["Fighter Pilot", "Glide Bomb", "Mortar Strike"], "2piece": 4, "3piece": 0, "4piece": 0, "4streak": 1, "5streak": 0, "6streak": 0, "7streak": 0, "8+streak": 0, "scorestreaks_earned": 2, "scorestreaks_used": 2, "scorestreaks_deployed": 2, "scorestreaks_kills": 3, "scorestreaks_assists": 0, "hp_hill_time_s": 86, "hp_captures": 0, "hp_defends": 2}, {"name": "REPLAYS", "team": "FAZE CLAN", "kills": 20, "deaths": 20, "kd": 1.0, "kills_per_10min": 22.6, "deaths_per_10min": 22.6, "assists": 6, "headshots": 1, "suicides": 0, "team_kills": 0, "team_deaths": 1, "stayed_alive_kills": 14, "hits": 63, "shots": 259, "accuracy": 24.3, "num_lives": 22, "time_alive_s": 486.2, "avg_time_per_life_s": 22.1, "fave_weapon": "BAR", "fave_division": "Infantry", "fave_training": "Hunker", "fave_scorestreaks": ["Fighter Pilot", "Glide Bomb", "Mortar Strike"], "2piece": 2, "3piece": 0, "4piece": 0, "4streak": 0, "5streak": 0, "6streak": 0, "7streak": 0, "8+streak": 0, "scorestreaks_earned": 0, "scorestreaks_used": 0, "scorestreaks_deployed": 0, "scorestreaks_kills": 0, "scorestreaks_assists": 0, "hp_hill_time_s": 68, "hp_captures": 0, "hp_defends": 2}, {"name": "ZOOMAA", "team": "FAZE CLAN", "kills": 34, "deaths": 22, "kd": 1.55, "kills_per_10min": 38.5, "deaths_per_10min": 24.9, "assists": 11, "headshots": 4, "suicides": 0, "team_kills": 1, "team_deaths": 0, "stayed_alive_kills": 24, "hits": 160, "shots": 522, "accuracy": 30.7, "num_lives": 23, "time_alive_s": 485.6, "avg_time_per_life_s": 21.1, "fave_weapon": "PPSh-41", "fave_division": "Airborne", "fave_training": "Hunker", "fave_scorestreaks": ["Fighter Pilot", "Glide Bomb", "Mortar Strike"], "2piece": 7, "3piece": 1, "4piece": 0, "4streak": 2, "5streak": 0, "6streak": 0, "7streak": 0, "8+streak": 0, "scorestreaks_earned": 0, "scorestreaks_used": 0, "scorestreaks_deployed": 0, "scorestreaks_kills": 0, "scorestreaks_assists": 0, "hp_hill_time_s": 65, "hp_captures": 0, "hp_defends": 3}], "events": [{"type": "roundstart", "time_ms": 0, "round": 1, "round_time_ms": 0, "data": {}}, {"type": "spawn", "time_ms": 0, "round": 1, "round_time_ms": 0, "data": {"id": "ZOOMAA", "pos": {"y": 446, "x": 137}, "life": 0}}, {"type": "spawn", "time_ms": 0, "round": 1, "round_time_ms": 0, "data": {"id": "PRIESTAH", "pos": {"y": 425, "x": 128}, "life": 1}}, {"type": "spawn", "time_ms": 0, "round": 1, "round_time_ms": 0, "data": {"id": "FIGHTA", "pos": {"y": 561, "x": 885}, "life": 2}}, {"type": "spawn", "time_ms": 0, "round": 1, "round_time_ms": 0, "data": {"id": "SHOCKZ", "pos": {"y": 570, "x": 872}, "life": 3}}, {"type": "spawn", "time_ms": 0, "round": 1, "round_time_ms": 0, "data": {"id": "REPLAYS", "pos": {"y": 420, "x": 146}, "life": 4}}, {"type": "spawn", "time_ms": 0, "round": 1, "round_time_ms": 0, "data": {"id": "ATTACH", "pos": {"y": 412, "x": 135}, "life": 5}}, {"type": "spawn", "time_ms": 0, "round": 1, "round_time_ms": 0, "data": {"id": "DENZ", "pos": {"y": 578, "x": 896}, "life": 6}}, {"type": "spawn", "time_ms": 0, "round": 1, "round_time_ms": 0, "data": {"id": "BUZZO", "pos": {"y": 587, "x": 916}, "life": 7}}, {"type": "death", "time_ms": 12500, "round": 1, "round_time_ms": 12500, "data": {"id": "FIGHTA", "attacker": {"means_of_death": "rifle_bullet", "id": "REPLAYS", "pos": {"y": 403, "x": 446}, "weapon": "BAR", "life": 4}, "pos": {"y": 271, "x": 624}, "life": 2}}, {"type": "spawn", "time_ms": 14550, "round": 1, "round_time_ms": 14550, "data": {"id": "FIGHTA", "pos": {"y": 547, "x": 895}, "life": 8}}, {"type": "death", "time_ms": 17900, "round": 1, "round_time_ms": 17900, "data": {"id": "DENZ", "attacker": {"means_of_death": "pistol_bullet", "id": "ATTACH", "pos": {"y": 214, "x": 537}, "weapon": "PPSh-41", "life": 5}, "pos": {"y": 279, "x": 574}, "life": 6}}, {"type": "death", "time_ms": 19200, "round": 1, "round_time_ms": 19200, "data": {"id": "PRIESTAH", "attacker": {"means_of_death": "pistol_bullet", "id": "SHOCKZ", "pos": {"y": 418, "x": 619}, "weapon": "PPSh-41", "life": 3}, "pos": {"y": 528, "x": 630}, "life": 1}}, {"type": "spawn", "time_ms": 19950, "round": 1, "round_time_ms": 19950, "data": {"id": "DENZ", "pos": {"y": 547, "x": 895}, "life": 9}}, {"type": "death", "time_ms": 20700, "round": 1, "round_time_ms": 20700, "data": {"id": "FIGHTA", "attacker": {"means_of_death": "pistol_bullet", "id": "ZOOMAA", "pos": {"y": 508, "x": 557}, "weapon": "PPSh-41", "life": 0}, "pos": {"y": 488, "x": 649}, "life": 8}}, {"type": "spawn", "time_ms": 21250, "round": 1, "round_time_ms": 21250, "data": {"id": "PRIESTAH", "pos": {"y": 344, "x": 173}, "life": 10}}, {"type": "spawn", "time_ms": 22750, "round": 1, "round_time_ms": 22750, "data": {"id": "FIGHTA", "pos": {"y": 627, "x": 984}, "life": 11}}, {"type": "death", "time_ms": 23250, "round": 1, "round_time_ms": 23250, "data": {"id": "ZOOMAA", "attacker": {"means_of_death": "rifle_bullet", "id": "DENZ", "pos": {"y": 518, "x": 795}, "weapon": "FG 42", "life": 9}, "pos": {"y": 490, "x": 594}, "life": 0}}, {"type": "spawn", "time_ms": 25300, "round": 1, "round_time_ms": 25300, "data": {"id": "ZOOMAA", "pos": {"y": 349, "x": 91}, "life": 12}}, {"type": "death", "time_ms": 27250, "round": 1, "round_time_ms": 27250, "data": {"id": "PRIESTAH", "attacker": {"means_of_death": "head_shot", "id": "SHOCKZ", "pos": {"y": 375, "x": 562}, "weapon": "PPSh-41", "life": 3}, "pos": {"y": 358, "x": 399}, "life": 10}}, {"type": "death", "time_ms": 28950, "round": 1, "round_time_ms": 28950, "data": {"id": "SHOCKZ", "attacker": {"means_of_death": "pistol_bullet", "id": "ATTACH", "pos": {"y": 289, "x": 489}, "weapon": "PPSh-41", "life": 5}, "pos": {"y": 353, "x": 541}, "life": 3}}, {"type": "spawn", "time_ms": 29300, "round": 1, "round_time_ms": 29300, "data": {"id": "PRIESTAH", "pos": {"y": 344, "x": 173}, "life": 13}}, {"type": "death", "time_ms": 30550, "round": 1, "round_time_ms": 30550, "data": {"id": "REPLAYS", "attacker": {"means_of_death": "pistol_bullet", "id": "FIGHTA", "pos": {"y": 488, "x": 669}, "weapon": "PPSh-41", "life": 11}, "pos": {"y": 517, "x": 604}, "life": 4}}, {"type": "spawn", "time_ms": 31000, "round": 1, "round_time_ms": 31000, "data": {"id": "SHOCKZ", "pos": {"y": 499, "x": 892}, "life": 14}}, {"type": "death", "time_ms": 31600, "round": 1, "round_time_ms": 31600, "data": {"id": "BUZZO", "attacker": {"means_of_death": "grenade_splash", "id": "ZOOMAA", "pos": {"y": 327, "x": 307}, "weapon": "No 74 ST", "life": 12}, "pos": {"y": 214, "x": 536}, "life": 7}}, {"type": "spawn", "time_ms": 33000, "round": 1, "round_time_ms": 33000, "data": {"id": "REPLAYS", "pos": {"y": 356, "x": 219}, "life": 15}}, {"type": "spawn", "time_ms": 33650, "round": 1, "round_time_ms": 33650, "data": {"id": "BUZZO", "pos": {"y": 444, "x": 816}, "life": 16}}, {"type": "death", "time_ms": 38050, "round": 1, "round_time_ms": 38050, "data": {"id": "PRIESTAH", "attacker": {"means_of_death": "rifle_bullet", "id": "DENZ", "pos": {"y": 366, "x": 561}, "weapon": "FG 42", "life": 9}, "pos": {"y": 381, "x": 398}, "life": 13}}, {"type": "death", "time_ms": 39900, "round": 1, "round_time_ms": 39900, "data": {"id": "DENZ", "attacker": {"means_of_death": "pistol_bullet", "id": "ATTACH", "pos": {"y": 282, "x": 490}, "weapon": "PPSh-41", "life": 5}, "pos": {"y": 374, "x": 569}, "life": 9}}, {"type": "spawn", "time_ms": 40100, "round": 1, "round_time_ms": 40100, "data": {"id": "PRIESTAH", "pos": {"y": 603, "x": 268}, "life": 17}}, {"type": "spawn", "time_ms": 41950, "round": 1, "round_time_ms": 41950, "data": {"id": "DENZ", "pos": {"y": 547, "x": 895}, "life": 18}}, {"type": "death", "time_ms": 44350, "round": 1, "round_time_ms": 44350, "data": {"id": "ATTACH", "attacker": {"means_of_death": "pistol_bullet", "id": "SHOCKZ", "pos": {"y": 232, "x": 476}, "weapon": "PPSh-41", "life": 14}, "pos": {"y": 273, "x": 479}, "life": 5}}, {"type": "death", "time_ms": 44750, "round": 1, "round_time_ms": 44750, "data": {"id": "FIGHTA", "attacker": {"means_of_death": "pistol_bullet", "id": "ZOOMAA", "pos": {"y": 449, "x": 627}, "weapon": "PPSh-41", "life": 12}, "pos": {"y": 225, "x": 560}, "life": 11}}, {"type": "spawn", "time_ms": 46400, "round": 1, "round_time_ms": 46400, "data": {"id": "ATTACH", "pos": {"y": 349, "x": 91}, "life": 19}}, {"type": "death", "time_ms": 46400, "round": 1, "round_time_ms": 46400, "data": {"id": "BUZZO", "attacker": {"means_of_death": "pistol_bullet", "id": "ZOOMAA", "pos": {"y": 437, "x": 604}, "weapon": "PPSh-41", "life": 12}, "pos": {"y": 302, "x": 605}, "life": 16}}, {"type": "spawn", "time_ms": 46800, "round": 1, "round_time_ms": 46800, "data": {"id": "FIGHTA", "pos": {"y": 627, "x": 984}, "life": 20}}, {"type": "death", "time_ms": 48150, "round": 1, "round_time_ms": 48150, "data": {"id": "ZOOMAA", "attacker": {"means_of_death": "pistol_bullet", "id": "SHOCKZ", "pos": {"y": 296, "x": 451}, "weapon": "PPSh-41", "life": 14}, "pos": {"y": 381, "x": 570}, "life": 12}}, {"type": "spawn", "time_ms": 50050, "round": 1, "round_time_ms": 50050, "data": {"id": "BUZZO", "pos": {"y": 391, "x": 802}, "life": 21}}, {"type": "death", "time_ms": 50100, "round": 1, "round_time_ms": 50100, "data": {"id": "DENZ", "attacker": {"means_of_death": "rifle_bullet", "id": "PRIESTAH", "pos": {"y": 746, "x": 484}, "weapon": "STG-44", "life": 17}, "pos": {"y": 701, "x": 660}, "life": 18}}, {"type": "spawn", "time_ms": 50200, "round": 1, "round_time_ms": 50200, "data": {"id": "ZOOMAA", "pos": {"y": 356, "x": 219}, "life": 22}}, {"type": "spawn", "time_ms": 54000, "round": 1, "round_time_ms": 54000, "data": {"id": "DENZ", "pos": {"y": 444, "x": 816}, "life": 23}}, {"type": "death", "time_ms": 54700, "round": 1, "round_time_ms": 54700, "data": {"id": "SHOCKZ", "attacker": {"means_of_death": "pistol_bullet", "id": "ZOOMAA", "pos": {"y": 505, "x": 290}, "weapon": "PPSh-41", "life": 22}, "pos": {"y": 517, "x": 405}, "life": 14}}, {"type": "spawn", "time_ms": 56750, "round": 1, "round_time_ms": 56750, "data": {"id": "SHOCKZ", "pos": {"y": 499, "x": 892}, "life": 24}}, {"type": "death", "time_ms": 57900, "round": 1, "round_time_ms": 57900, "data": {"id": "FIGHTA", "attacker": {"means_of_death": "rifle_bullet", "id": "PRIESTAH", "pos": {"y": 750, "x": 484}, "weapon": "STG-44", "life": 17}, "pos": {"y": 697, "x": 617}, "life": 20}}, {"type": "spawn", "time_ms": 59950, "round": 1, "round_time_ms": 59950, "data": {"id": "FIGHTA", "pos": {"y": 499, "x": 892}, "life": 25}}, {"type": "death", "time_ms": 65900, "round": 1, "round_time_ms": 65900, "data": {"id": "DENZ", "attacker": {"means_of_death": "pistol_bullet", "id": "ZOOMAA", "pos": {"y": 698, "x": 577}, "weapon": "PPSh-41", "life": 22}, "pos": {"y": 629, "x": 607}, "life": 23}}, {"type": "death", "time_ms": 67650, "round": 1, "round_time_ms": 67650, "data": {"id": "BUZZO", "attacker": {"means_of_death": "pistol_bullet", "id": "ZOOMAA", "pos": {"y": 712, "x": 586}, "weapon": "PPSh-41", "life": 22}, "pos": {"y": 679, "x": 736}, "life": 21}}, {"type": "death", "time_ms": 67700, "round": 1, "round_time_ms": 67700, "data": {"id": "ZOOMAA", "attacker": {"means_of_death": "pistol_bullet", "id": "FIGHTA", "pos": {"y": 678, "x": 648}, "weapon": "PPSh-41", "life": 25}, "pos": {"y": 712, "x": 585}, "life": 22}}, {"type": "spawn", "time_ms": 67950, "round": 1, "round_time_ms": 67950, "data": {"id": "DENZ", "pos": {"y": 658, "x": 926}, "life": 26}}, {"type": "spawn", "time_ms": 69700, "round": 1, "round_time_ms": 69700, "data": {"id": "BUZZO", "pos": {"y": 658, "x": 926}, "life": 27}}, {"type": "spawn", "time_ms": 69750, "round": 1, "round_time_ms": 69750, "data": {"id": "ZOOMAA", "pos": {"y": 499, "x": 199}, "life": 28}}, {"type": "death", "time_ms": 76250, "round": 1, "round_time_ms": 76250, "data": {"id": "FIGHTA", "attacker": {"means_of_death": "pistol_bullet", "id": "PRIESTAH", "pos": {"y": 763, "x": 516}, "weapon": "Machine Pistol", "life": 17}, "pos": {"y": 745, "x": 585}, "life": 25}}, {"type": "death", "time_ms": 76800, "round": 1, "round_time_ms": 76800, "data": {"id": "REPLAYS", "attacker": {"means_of_death": "pistol_bullet", "id": "SHOCKZ", "pos": {"y": 680, "x": 494}, "weapon": "PPSh-41", "life": 24}, "pos": {"y": 616, "x": 479}, "life": 15}}, {"type": "death", "time_ms": 77650, "round": 1, "round_time_ms": 77650, "data": {"id": "PRIESTAH", "attacker": {"means_of_death": "rifle_bullet", "id": "DENZ", "pos": {"y": 724, "x": 651}, "weapon": "STG-44", "life": 26}, "pos": {"y": 767, "x": 481}, "life": 17}}, {"type": "spawn", "time_ms": 78300, "round": 1, "round_time_ms": 78300, "data": {"id": "FIGHTA", "pos": {"y": 655, "x": 982}, "life": 29}}, {"type": "spawn", "time_ms": 78850, "round": 1, "round_time_ms": 78850, "data": {"id": "REPLAYS", "pos": {"y": 427, "x": 92}, "life": 30}}, {"type": "death", "time_ms": 79600, "round": 1, "round_time_ms": 79600, "data": {"id": "SHOCKZ", "attacker": {"means_of_death": "pistol_bullet", "id": "ZOOMAA", "pos": {"y": 614, "x": 484}, "weapon": "PPSh-41", "life": 28}, "pos": {"y": 634, "x": 480}, "life": 24}}, {"type": "spawn", "time_ms": 79700, "round": 1, "round_time_ms": 79700, "data": {"id": "PRIESTAH", "pos": {"y": 460, "x": 162}, "life": 31}}, {"type": "spawn", "time_ms": 81650, "round": 1, "round_time_ms": 81650, "data": {"id": "SHOCKZ", "pos": {"y": 658, "x": 926}, "life": 32}}, {"type": "death", "time_ms": 83950, "round": 1, "round_time_ms": 83950, "data": {"id": "ATTACH", "attacker": {"means_of_death": "rifle_bullet", "id": "BUZZO", "pos": {"y": 708, "x": 610}, "weapon": "FG 42", "life": 27}, "pos": {"y": 734, "x": 573}, "life": 19}}, {"type": "spawn", "time_ms": 86000, "round": 1, "round_time_ms": 86000, "data": {"id": "ATTACH", "pos": {"y": 460, "x": 162}, "life": 33}}, {"type": "death", "time_ms": 86700, "round": 1, "round_time_ms": 86700, "data": {"id": "ZOOMAA", "attacker": {"means_of_death": "rifle_bullet", "id": "BUZZO", "pos": {"y": 710, "x": 607}, "weapon": "FG 42", "life": 27}, "pos": {"y": 706, "x": 495}, "life": 28}}, {"type": "death", "time_ms": 87650, "round": 1, "round_time_ms": 87650, "data": {"id": "BUZZO", "attacker": {"means_of_death": "grenade_splash", "id": "REPLAYS", "pos": {"y": 567, "x": 407}, "weapon": "Stielhandgranate", "life": 30}, "pos": {"y": 711, "x": 604}, "life": 27}}, {"type": "death", "time_ms": 88700, "round": 1, "round_time_ms": 88700, "data": {"id": "DENZ", "attacker": {"means_of_death": "grenade_splash", "id": "PRIESTAH", "pos": {"y": 726, "x": 323}, "weapon": "Stielhandgranate", "life": 31}, "pos": {"y": 760, "x": 505}, "life": 26}}, {"type": "death", "time_ms": 88700, "round": 1, "round_time_ms": 88700, "data": {"id": "FIGHTA", "attacker": {"means_of_death": "grenade_splash", "id": "PRIESTAH", "pos": {"y": 726, "x": 323}, "weapon": "Stielhandgranate", "life": 31}, "pos": {"y": 741, "x": 573}, "life": 29}}, {"type": "spawn", "time_ms": 88750, "round": 1, "round_time_ms": 88750, "data": {"id": "ZOOMAA", "pos": {"y": 553, "x": 227}, "life": 34}}, {"type": "spawn", "time_ms": 89700, "round": 1, "round_time_ms": 89700, "data": {"id": "BUZZO", "pos": {"y": 667, "x": 918}, "life": 35}}, {"type": "spawn", "time_ms": 90750, "round": 1, "round_time_ms": 90750, "data": {"id": "DENZ", "pos": {"y": 669, "x": 896}, "life": 36}}, {"type": "spawn", "time_ms": 90800, "round": 1, "round_time_ms": 90800, "data": {"id": "FIGHTA", "pos": {"y": 667, "x": 918}, "life": 37}}, {"type": "death", "time_ms": 94400, "round": 1, "round_time_ms": 94400, "data": {"id": "SHOCKZ", "attacker": {"means_of_death": "rifle_bullet", "id": "REPLAYS", "pos": {"y": 598, "x": 506}, "weapon": "BAR", "life": 30}, "pos": {"y": 608, "x": 540}, "life": 32}}, {"type": "spawn", "time_ms": 96450, "round": 1, "round_time_ms": 96450, "data": {"id": "SHOCKZ", "pos": {"y": 655, "x": 982}, "life": 38}}, {"type": "death", "time_ms": 101300, "round": 1, "round_time_ms": 101300, "data": {"id": "ATTACH", "attacker": {"means_of_death": "rifle_bullet", "id": "DENZ", "pos": {"y": 732, "x": 581}, "weapon": "STG-44", "life": 36}, "pos": {"y": 705, "x": 401}, "life": 33}}, {"type": "death", "time_ms": 101450, "round": 1, "round_time_ms": 101450, "data": {"id": "DENZ", "attacker": {"means_of_death": "pistol_bullet", "id": "ZOOMAA", "pos": {"y": 705, "x": 501}, "weapon": "PPSh-41", "life": 34}, "pos": {"y": 732, "x": 581}, "life": 36}}, {"type": "spawn", "time_ms": 103350, "round": 1, "round_time_ms": 103350, "data": {"id": "ATTACH", "pos": {"y": 427, "x": 92}, "life": 39}}, {"type": "spawn", "time_ms": 103500, "round": 1, "round_time_ms": 103500, "data": {"id": "DENZ", "pos": {"y": 655, "x": 982}, "life": 40}}, {"type": "death", "time_ms": 103650, "round": 1, "round_time_ms": 103650, "data": {"id": "BUZZO", "attacker": {"means_of_death": "pistol_bullet", "id": "ZOOMAA", "pos": {"y": 716, "x": 501}, "weapon": "PPSh-41", "life": 34}, "pos": {"y": 721, "x": 618}, "life": 35}}, {"type": "spawn", "time_ms": 105700, "round": 1, "round_time_ms": 105700, "data": {"id": "BUZZO", "pos": {"y": 604, "x": 972}, "life": 41}}, {"type": "death", "time_ms": 107200, "round": 1, "round_time_ms": 107200, "data": {"id": "FIGHTA", "attacker": {"means_of_death": "rifle_bullet", "id": "PRIESTAH", "pos": {"y": 762, "x": 474}, "weapon": "STG-44", "life": 31}, "pos": {"y": 617, "x": 483}, "life": 37}}, {"type": "spawn", "time_ms": 109250, "round": 1, "round_time_ms": 109250, "data": {"id": "FIGHTA", "pos": {"y": 499, "x": 892}, "life": 42}}, {"type": "death", "time_ms": 111200, "round": 1, "round_time_ms": 111200, "data": {"id": "SHOCKZ", "attacker": {"means_of_death": "pistol_bullet", "id": "ZOOMAA", "pos": {"y": 703, "x": 469}, "weapon": "PPSh-41", "life": 34}, "pos": {"y": 672, "x": 533}, "life": 38}}, {"type": "spawn", "time_ms": 113250, "round": 1, "round_time_ms": 113250, "data": {"id": "SHOCKZ", "pos": {"y": 658, "x": 926}, "life": 43}}, {"type": "death", "time_ms": 122650, "round": 1, "round_time_ms": 122650, "data": {"id": "REPLAYS", "attacker": {"means_of_death": "head_shot", "id": "FIGHTA", "pos": {"y": 224, "x": 496}, "weapon": "PPSh-41", "life": 42}, "pos": {"y": 262, "x": 465}, "life": 30}}, {"type": "spawn", "time_ms": 124700, "round": 1, "round_time_ms": 124700, "data": {"id": "REPLAYS", "pos": {"y": 689, "x": 296}, "life": 44}}, {"type": "death", "time_ms": 125900, "round": 1, "round_time_ms": 125900, "data": {"id": "FIGHTA", "attacker": {"means_of_death": "rifle_bullet", "id": "BUZZO", "pos": {"y": 225, "x": 509}, "weapon": "FG 42", "life": 41}, "pos": {"y": 307, "x": 419}, "life": 42}}, {"type": "spawn", "time_ms": 127950, "round": 1, "round_time_ms": 127950, "data": {"id": "FIGHTA", "pos": {"y": 499, "x": 892}, "life": 45}}, {"type": "death", "time_ms": 130600, "round": 1, "round_time_ms": 130600, "data": {"id": "DENZ", "attacker": {"means_of_death": "pistol_bullet", "id": "ZOOMAA", "pos": {"y": 460, "x": 456}, "weapon": "PPSh-41", "life": 34}, "pos": {"y": 349, "x": 486}, "life": 40}}, {"type": "death", "time_ms": 132400, "round": 1, "round_time_ms": 132400, "data": {"id": "ATTACH", "attacker": {"means_of_death": "grenade_splash", "id": "DENZ", "pos": {"y": 349, "x": 486}, "weapon": "Mk2 Frag Grenade", "life": 40}, "pos": {"y": 377, "x": 355}, "life": 39}}, {"type": "spawn", "time_ms": 132650, "round": 1, "round_time_ms": 132650, "data": {"id": "DENZ", "pos": {"y": 349, "x": 91}, "life": 46}}, {"type": "death", "time_ms": 134400, "round": 1, "round_time_ms": 134400, "data": {"id": "PRIESTAH", "attacker": {"means_of_death": "pistol_bullet", "id": "FIGHTA", "pos": {"y": 501, "x": 683}, "weapon": "PPSh-41", "life": 45}, "pos": {"y": 507, "x": 550}, "life": 31}}, {"type": "spawn", "time_ms": 134450, "round": 1, "round_time_ms": 134450, "data": {"id": "ATTACH", "pos": {"y": 748, "x": 328}, "life": 47}}, {"type": "spawn", "time_ms": 136450, "round": 1, "round_time_ms": 136450, "data": {"id": "PRIESTAH", "pos": {"y": 748, "x": 328}, "life": 48}}, {"type": "death", "time_ms": 139050, "round": 1, "round_time_ms": 139050, "data": {"id": "SHOCKZ", "attacker": {"means_of_death": "rifle_bullet", "id": "REPLAYS", "pos": {"y": 368, "x": 329}, "weapon": "BAR", "life": 44}, "pos": {"y": 332, "x": 354}, "life": 43}}, {"type": "spawn", "time_ms": 141100, "round": 1, "round_time_ms": 141100, "data": {"id": "SHOCKZ", "pos": {"y": 391, "x": 802}, "life": 49}}, {"type": "death", "time_ms": 142000, "round": 1, "round_time_ms": 142000, "data": {"id": "DENZ", "attacker": {"means_of_death": "rifle_bullet", "id": "PRIESTAH", "pos": {"y": 575, "x": 263}, "weapon": "STG-44", "life": 48}, "pos": {"y": 406, "x": 141}, "life": 46}}, {"type": "death", "time_ms": 142400, "round": 1, "round_time_ms": 142400, "data": {"id": "REPLAYS", "attacker": {"means_of_death": "pistol_bullet", "id": "FIGHTA", "pos": {"y": 365, "x": 425}, "weapon": "PPSh-41", "life": 45}, "pos": {"y": 344, "x": 395}, "life": 44}}, {"type": "spawn", "time_ms": 144050, "round": 1, "round_time_ms": 144050, "data": {"id": "DENZ", "pos": {"y": 676, "x": 735}, "life": 50}}, {"type": "spawn", "time_ms": 144450, "round": 1, "round_time_ms": 144450, "data": {"id": "REPLAYS", "pos": {"y": 716, "x": 312}, "life": 51}}, {"type": "death", "time_ms": 145450, "round": 1, "round_time_ms": 145450, "data": {"id": "ZOOMAA", "attacker": {"means_of_death": "pistol_bullet", "id": "SHOCKZ", "pos": {"y": 411, "x": 615}, "weapon": "PPSh-41", "life": 49}, "pos": {"y": 363, "x": 555}, "life": 34}}, {"type": "spawn", "time_ms": 147500, "round": 1, "round_time_ms": 147500, "data": {"id": "ZOOMAA", "pos": {"y": 427, "x": 92}, "life": 52}}, {"type": "death", "time_ms": 150250, "round": 1, "round_time_ms": 150250, "data": {"id": "ATTACH", "attacker": {"means_of_death": "pistol_bullet", "id": "FIGHTA", "pos": {"y": 338, "x": 344}, "weapon": "PPSh-41", "life": 45}, "pos": {"y": 368, "x": 338}, "life": 47}}, {"type": "spawn", "time_ms": 152300, "round": 1, "round_time_ms": 152300, "data": {"id": "ATTACH", "pos": {"y": 499, "x": 892}, "life": 53}}, {"type": "death", "time_ms": 153850, "round": 1, "round_time_ms": 153850, "data": {"id": "REPLAYS", "attacker": {"means_of_death": "rifle_bullet", "id": "DENZ", "pos": {"y": 572, "x": 487}, "weapon": "STG-44", "life": 50}, "pos": {"y": 567, "x": 409}, "life": 51}}, {"type": "spawn", "time_ms": 155900, "round": 1, "round_time_ms": 155900, "data": {"id": "REPLAYS", "pos": {"y": 391, "x": 802}, "life": 54}}, {"type": "death", "time_ms": 157500, "round": 1, "round_time_ms": 157500, "data": {"id": "SHOCKZ", "attacker": {"means_of_death": "pistol_bullet", "id": "PRIESTAH", "pos": {"y": 334, "x": 342}, "weapon": "PPSh-41", "life": 48}, "pos": {"y": 331, "x": 346}, "life": 49}}, {"type": "death", "time_ms": 158200, "round": 1, "round_time_ms": 158200, "data": {"id": "PRIESTAH", "attacker": {"means_of_death": "grenade_splash", "id": "ZOOMAA", "pos": {"y": 356, "x": 322}, "weapon": "No 74 ST", "life": 52}, "pos": {"y": 345, "x": 344}, "life": 48}}, {"type": "spawn", "time_ms": 159550, "round": 1, "round_time_ms": 159550, "data": {"id": "SHOCKZ", "pos": {"y": 748, "x": 328}, "life": 55}}, {"type": "spawn", "time_ms": 160250, "round": 1, "round_time_ms": 160250, "data": {"id": "PRIESTAH", "pos": {"y": 499, "x": 892}, "life": 56}}, {"type": "death", "time_ms": 160250, "round": 1, "round_time_ms": 160250, "data": {"id": "FIGHTA", "attacker": {"means_of_death": "pistol_bullet", "id": "ZOOMAA", "pos": {"y": 331, "x": 346}, "weapon": "PPSh-41", "life": 52}, "pos": {"y": 336, "x": 395}, "life": 45}}, {"type": "spawn", "time_ms": 162300, "round": 1, "round_time_ms": 162300, "data": {"id": "FIGHTA", "pos": {"y": 689, "x": 296}, "life": 57}}, {"type": "death", "time_ms": 162600, "round": 1, "round_time_ms": 162600, "data": {"id": "BUZZO", "attacker": {"means_of_death": "pistol_bullet", "id": "ZOOMAA", "pos": {"y": 354, "x": 351}, "weapon": "PPSh-41", "life": 52}, "pos": {"y": 368, "x": 302}, "life": 41}}, {"type": "spawn", "time_ms": 164650, "round": 1, "round_time_ms": 164650, "data": {"id": "BUZZO", "pos": {"y": 748, "x": 328}, "life": 58}}, {"type": "death", "time_ms": 166550, "round": 1, "round_time_ms": 166550, "data": {"id": "DENZ", "attacker": {"means_of_death": "rifle_bullet", "id": "REPLAYS", "pos": {"y": 346, "x": 481}, "weapon": "BAR", "life": 54}, "pos": {"y": 469, "x": 460}, "life": 50}}, {"type": "death", "time_ms": 167650, "round": 1, "round_time_ms": 167650, "data": {"id": "SHOCKZ", "attacker": {"means_of_death": "pistol_bullet", "id": "ZOOMAA", "pos": {"y": 363, "x": 313}, "weapon": "PPSh-41", "life": 52}, "pos": {"y": 455, "x": 211}, "life": 55}}, {"type": "spawn", "time_ms": 168600, "round": 1, "round_time_ms": 168600, "data": {"id": "DENZ", "pos": {"y": 499, "x": 892}, "life": 59}}, {"type": "spawn", "time_ms": 169700, "round": 1, "round_time_ms": 169700, "data": {"id": "SHOCKZ", "pos": {"y": 499, "x": 892}, "life": 60}}, {"type": "death", "time_ms": 174650, "round": 1, "round_time_ms": 174650, "data": {"id": "SHOCKZ", "attacker": {"means_of_death": "rifle_bullet", "id": "REPLAYS", "pos": {"y": 355, "x": 606}, "weapon": "BAR", "life": 54}, "pos": {"y": 352, "x": 737}, "life": 60}}, {"type": "death", "time_ms": 176650, "round": 1, "round_time_ms": 176650, "data": {"id": "ATTACH", "attacker": {"means_of_death": "pistol_bullet", "id": "FIGHTA", "pos": {"y": 483, "x": 630}, "weapon": "PPSh-41", "life": 57}, "pos": {"y": 385, "x": 592}, "life": 53}}, {"type": "spawn", "time_ms": 176700, "round": 1, "round_time_ms": 176700, "data": {"id": "SHOCKZ", "pos": {"y": 349, "x": 91}, "life": 61}}, {"type": "death", "time_ms": 178650, "round": 1, "round_time_ms": 178650, "data": {"id": "REPLAYS", "attacker": {"means_of_death": "pistol_bullet", "id": "FIGHTA", "pos": {"y": 461, "x": 615}, "weapon": "PPSh-41", "life": 57}, "pos": {"y": 306, "x": 613}, "life": 54}}, {"type": "spawn", "time_ms": 178700, "round": 1, "round_time_ms": 178700, "data": {"id": "ATTACH", "pos": {"y": 499, "x": 199}, "life": 62}}, {"type": "death", "time_ms": 180200, "round": 1, "round_time_ms": 180200, "data": {"id": "BUZZO", "attacker": {"means_of_death": "rifle_bullet", "id": "PRIESTAH", "pos": {"y": 638, "x": 483}, "weapon": "STG-44", "life": 56}, "pos": {"y": 667, "x": 503}, "life": 58}}, {"type": "spawn", "time_ms": 180700, "round": 1, "round_time_ms": 180700, "data": {"id": "REPLAYS", "pos": {"y": 748, "x": 328}, "life": 63}}, {"type": "death", "time_ms": 181250, "round": 1, "round_time_ms": 181250, "data": {"id": "SHOCKZ", "attacker": {"means_of_death": "pistol_bullet", "id": "ZOOMAA", "pos": {"y": 366, "x": 349}, "weapon": "PPSh-41", "life": 52}, "pos": {"y": 346, "x": 266}, "life": 61}}, {"type": "spawn", "time_ms": 183300, "round": 1, "round_time_ms": 183300, "data": {"id": "SHOCKZ", "pos": {"y": 499, "x": 892}, "life": 64}}, {"type": "spawn", "time_ms": 183550, "round": 1, "round_time_ms": 183550, "data": {"id": "BUZZO", "pos": {"y": 547, "x": 895}, "life": 65}}, {"type": "death", "time_ms": 188350, "round": 1, "round_time_ms": 188350, "data": {"id": "ZOOMAA", "attacker": {"means_of_death": "rifle_bullet", "id": "DENZ", "pos": {"y": 330, "x": 638}, "weapon": "STG-44", "life": 59}, "pos": {"y": 287, "x": 347}, "life": 52}}, {"type": "death", "time_ms": 189500, "round": 1, "round_time_ms": 189500, "data": {"id": "PRIESTAH", "attacker": {"means_of_death": "pistol_bullet", "id": "FIGHTA", "pos": {"y": 541, "x": 605}, "weapon": "PPSh-41", "life": 57}, "pos": {"y": 534, "x": 540}, "life": 56}}, {"type": "spawn", "time_ms": 190400, "round": 1, "round_time_ms": 190400, "data": {"id": "ZOOMAA", "pos": {"y": 344, "x": 173}, "life": 66}}, {"type": "spawn", "time_ms": 191550, "round": 1, "round_time_ms": 191550, "data": {"id": "PRIESTAH", "pos": {"y": 344, "x": 173}, "life": 67}}, {"type": "death", "time_ms": 195150, "round": 1, "round_time_ms": 195150, "data": {"id": "BUZZO", "attacker": {"means_of_death": "rifle_bullet", "id": "REPLAYS", "pos": {"y": 552, "x": 732}, "weapon": "BAR", "life": 63}, "pos": {"y": 505, "x": 724}, "life": 65}}, {"type": "spawn", "time_ms": 197200, "round": 1, "round_time_ms": 197200, "data": {"id": "BUZZO", "pos": {"y": 748, "x": 328}, "life": 68}}, {"type": "death", "time_ms": 199400, "round": 1, "round_time_ms": 199400, "data": {"id": "REPLAYS", "attacker": {"means_of_death": "pistol_bullet", "id": "ATTACH", "pos": {"y": 515, "x": 479}, "weapon": "PPSh-41", "life": 62}, "pos": {"y": 486, "x": 707}, "life": 63}}, {"type": "spawn", "time_ms": 201450, "round": 1, "round_time_ms": 201450, "data": {"id": "REPLAYS", "pos": {"y": 349, "x": 91}, "life": 69}}, {"type": "death", "time_ms": 202950, "round": 1, "round_time_ms": 202950, "data": {"id": "ATTACH", "attacker": {"means_of_death": "head_shot", "id": "DENZ", "pos": {"y": 512, "x": 470}, "weapon": "STG-44", "life": 59}, "pos": {"y": 543, "x": 548}, "life": 62}}, {"type": "death", "time_ms": 204750, "round": 1, "round_time_ms": 204750, "data": {"id": "PRIESTAH", "attacker": {"means_of_death": "rifle_bullet", "id": "BUZZO", "pos": {"y": 603, "x": 511}, "weapon": "BAR", "life": 68}, "pos": {"y": 514, "x": 479}, "life": 67}}, {"type": "spawn", "time_ms": 205000, "round": 1, "round_time_ms": 205000, "data": {"id": "ATTACH", "pos": {"y": 427, "x": 92}, "life": 70}}, {"type": "spawn", "time_ms": 206800, "round": 1, "round_time_ms": 206800, "data": {"id": "PRIESTAH", "pos": {"y": 427, "x": 92}, "life": 71}}, {"type": "death", "time_ms": 209100, "round": 1, "round_time_ms": 209100, "data": {"id": "ZOOMAA", "attacker": {"means_of_death": "rifle_bullet", "id": "DENZ", "pos": {"y": 371, "x": 496}, "weapon": "STG-44", "life": 59}, "pos": {"y": 363, "x": 596}, "life": 66}}, {"type": "spawn", "time_ms": 211150, "round": 1, "round_time_ms": 211150, "data": {"id": "ZOOMAA", "pos": {"y": 460, "x": 162}, "life": 72}}, {"type": "death", "time_ms": 213400, "round": 1, "round_time_ms": 213400, "data": {"id": "ATTACH", "attacker": {"means_of_death": "rifle_bullet", "id": "DENZ", "pos": {"y": 365, "x": 556}, "weapon": "STG-44", "life": 59}, "pos": {"y": 375, "x": 420}, "life": 70}}, {"type": "spawn", "time_ms": 215450, "round": 1, "round_time_ms": 215450, "data": {"id": "ATTACH", "pos": {"y": 655, "x": 982}, "life": 73}}, {"type": "death", "time_ms": 216950, "round": 1, "round_time_ms": 216950, "data": {"id": "DENZ", "attacker": {"means_of_death": "rifle_bullet", "id": "PRIESTAH", "pos": {"y": 515, "x": 426}, "weapon": "STG-44", "life": 71}, "pos": {"y": 376, "x": 484}, "life": 59}}, {"type": "spawn", "time_ms": 219000, "round": 1, "round_time_ms": 219000, "data": {"id": "DENZ", "pos": {"y": 344, "x": 173}, "life": 74}}, {"type": "death", "time_ms": 219000, "round": 1, "round_time_ms": 219000, "data": {"id": "BUZZO", "attacker": {"means_of_death": "head_shot", "id": "ZOOMAA", "pos": {"y": 564, "x": 411}, "weapon": "PPSh-41", "life": 72}, "pos": {"y": 507, "x": 558}, "life": 68}}, {"type": "death", "time_ms": 220450, "round": 1, "round_time_ms": 220450, "data": {"id": "PRIESTAH", "attacker": {"means_of_death": "pistol_bullet", "id": "SHOCKZ", "pos": {"y": 383, "x": 473}, "weapon": "PPSh-41", "life": 64}, "pos": {"y": 406, "x": 453}, "life": 71}}, {"type": "spawn", "time_ms": 221050, "round": 1, "round_time_ms": 221050, "data": {"id": "BUZZO", "pos": {"y": 356, "x": 219}, "life": 75}}, {"type": "spawn", "time_ms": 222500, "round": 1, "round_time_ms": 222500, "data": {"id": "PRIESTAH", "pos": {"y": 639, "x": 988}, "life": 76}}, {"type": "death", "time_ms": 222750, "round": 1, "round_time_ms": 222750, "data": {"id": "FIGHTA", "attacker": {"means_of_death": "rifle_bullet", "id": "REPLAYS", "pos": {"y": 536, "x": 565}, "weapon": "BAR", "life": 69}, "pos": {"y": 552, "x": 601}, "life": 57}}, {"type": "death", "time_ms": 224500, "round": 1, "round_time_ms": 224500, "data": {"id": "ATTACH", "attacker": {"means_of_death": "pistol_bullet", "id": "SHOCKZ", "pos": {"y": 423, "x": 591}, "weapon": "PPSh-41", "life": 64}, "pos": {"y": 483, "x": 646}, "life": 73}}, {"type": "spawn", "time_ms": 224800, "round": 1, "round_time_ms": 224800, "data": {"id": "FIGHTA", "pos": {"y": 217, "x": 392}, "life": 77}}, {"type": "death", "time_ms": 225350, "round": 1, "round_time_ms": 225350, "data": {"id": "SHOCKZ", "attacker": {"means_of_death": "rifle_bullet", "id": "REPLAYS", "pos": {"y": 540, "x": 626}, "weapon": "BAR", "life": 69}, "pos": {"y": 410, "x": 612}, "life": 64}}, {"type": "spawn", "time_ms": 226550, "round": 1, "round_time_ms": 226550, "data": {"id": "ATTACH", "pos": {"y": 547, "x": 895}, "life": 78}}, {"type": "spawn", "time_ms": 227400, "round": 1, "round_time_ms": 227400, "data": {"id": "SHOCKZ", "pos": {"y": 748, "x": 328}, "life": 79}}, {"type": "death", "time_ms": 228000, "round": 1, "round_time_ms": 228000, "data": {"id": "BUZZO", "attacker": {"means_of_death": "head_shot", "id": "ZOOMAA", "pos": {"y": 398, "x": 465}, "weapon": "PPSh-41", "life": 72}, "pos": {"y": 293, "x": 463}, "life": 75}}, {"type": "death", "time_ms": 229100, "round": 1, "round_time_ms": 229100, "data": {"id": "ZOOMAA", "attacker": {"means_of_death": "rifle_bullet", "id": "DENZ", "pos": {"y": 273, "x": 479}, "weapon": "STG-44", "life": 74}, "pos": {"y": 394, "x": 460}, "life": 72}}, {"type": "spawn", "time_ms": 230050, "round": 1, "round_time_ms": 230050, "data": {"id": "BUZZO", "pos": {"y": 356, "x": 219}, "life": 80}}, {"type": "spawn", "time_ms": 231150, "round": 1, "round_time_ms": 231150, "data": {"id": "ZOOMAA", "pos": {"y": 658, "x": 926}, "life": 81}}, {"type": "death", "time_ms": 233050, "round": 1, "round_time_ms": 233050, "data": {"id": "ATTACH", "attacker": {"means_of_death": "pistol_bullet", "id": "FIGHTA", "pos": {"y": 302, "x": 709}, "weapon": "PPSh-41", "life": 77}, "pos": {"y": 413, "x": 736}, "life": 78}}, {"type": "death", "time_ms": 235000, "round": 1, "round_time_ms": 235000, "data": {"id": "REPLAYS", "attacker": {"means_of_death": "pistol_bullet", "id": "SHOCKZ", "pos": {"y": 533, "x": 569}, "weapon": "PPSh-41", "life": 79}, "pos": {"y": 553, "x": 608}, "life": 69}}, {"type": "spawn", "time_ms": 235100, "round": 1, "round_time_ms": 235100, "data": {"id": "ATTACH", "pos": {"y": 655, "x": 982}, "life": 82}}, {"type": "spawn", "time_ms": 237050, "round": 1, "round_time_ms": 237050, "data": {"id": "REPLAYS", "pos": {"y": 639, "x": 988}, "life": 83}}, {"type": "death", "time_ms": 237900, "round": 1, "round_time_ms": 237900, "data": {"id": "SHOCKZ", "attacker": {"means_of_death": "rifle_bullet", "id": "PRIESTAH", "pos": {"y": 437, "x": 614}, "weapon": "STG-44", "life": 76}, "pos": {"y": 485, "x": 605}, "life": 79}}, {"type": "death", "time_ms": 238900, "round": 1, "round_time_ms": 238900, "data": {"id": "PRIESTAH", "attacker": {"means_of_death": "pistol_bullet", "id": "FIGHTA", "pos": {"y": 399, "x": 647}, "weapon": "PPSh-41", "life": 77}, "pos": {"y": 440, "x": 596}, "life": 76}}, {"type": "spawn", "time_ms": 239950, "round": 1, "round_time_ms": 239950, "data": {"id": "SHOCKZ", "pos": {"y": 553, "x": 227}, "life": 84}}, {"type": "spawn", "time_ms": 240950, "round": 1, "round_time_ms": 240950, "data": {"id": "PRIESTAH", "pos": {"y": 669, "x": 896}, "life": 85}}, {"type": "death", "time_ms": 241500, "round": 1, "round_time_ms": 241500, "data": {"id": "ZOOMAA", "attacker": {"means_of_death": "head_shot", "id": "DENZ", "pos": {"y": 282, "x": 489}, "weapon": "STG-44", "life": 74}, "pos": {"y": 489, "x": 654}, "life": 81}}, {"type": "spawn", "time_ms": 243550, "round": 1, "round_time_ms": 243550, "data": {"id": "ZOOMAA", "pos": {"y": 646, "x": 839}, "life": 86}}, {"type": "death", "time_ms": 250350, "round": 1, "round_time_ms": 250350, "data": {"id": "FIGHTA", "attacker": {"means_of_death": "rifle_bullet", "id": "PRIESTAH", "pos": {"y": 410, "x": 807}, "weapon": "STG-44", "life": 85}, "pos": {"y": 399, "x": 672}, "life": 77}}, {"type": "spawn", "time_ms": 252400, "round": 1, "round_time_ms": 252400, "data": {"id": "FIGHTA", "pos": {"y": 349, "x": 91}, "life": 87}}, {"type": "death", "time_ms": 254000, "round": 1, "round_time_ms": 254000, "data": {"id": "ATTACH", "attacker": {"means_of_death": "pistol_bullet", "id": "SHOCKZ", "pos": {"y": 476, "x": 444}, "weapon": "PPSh-41", "life": 84}, "pos": {"y": 519, "x": 482}, "life": 82}}, {"type": "death", "time_ms": 254100, "round": 1, "round_time_ms": 254100, "data": {"id": "BUZZO", "attacker": {"means_of_death": "pistol_bullet", "id": "ZOOMAA", "pos": {"y": 377, "x": 645}, "weapon": "PPSh-41", "life": 86}, "pos": {"y": 333, "x": 634}, "life": 80}}, {"type": "death", "time_ms": 255850, "round": 1, "round_time_ms": 255850, "data": {"id": "DENZ", "attacker": {"means_of_death": "rifle_bullet", "id": "PRIESTAH", "pos": {"y": 302, "x": 694}, "weapon": "STG-44", "life": 85}, "pos": {"y": 224, "x": 519}, "life": 74}}, {"type": "death", "time_ms": 255850, "round": 1, "round_time_ms": 255850, "data": {"id": "REPLAYS", "attacker": {"means_of_death": "pistol_bullet", "id": "SHOCKZ", "pos": {"y": 478, "x": 448}, "weapon": "PPSh-41", "life": 84}, "pos": {"y": 544, "x": 489}, "life": 83}}, {"type": "spawn", "time_ms": 256150, "round": 1, "round_time_ms": 256150, "data": {"id": "BUZZO", "pos": {"y": 344, "x": 173}, "life": 88}}, {"type": "spawn", "time_ms": 256200, "round": 1, "round_time_ms": 256200, "data": {"id": "ATTACH", "pos": {"y": 372, "x": 751}, "life": 89}}, {"type": "spawn", "time_ms": 257900, "round": 1, "round_time_ms": 257900, "data": {"id": "DENZ", "pos": {"y": 356, "x": 219}, "life": 90}}, {"type": "spawn", "time_ms": 257950, "round": 1, "round_time_ms": 257950, "data": {"id": "REPLAYS", "pos": {"y": 372, "x": 751}, "life": 91}}, {"type": "death", "time_ms": 262000, "round": 1, "round_time_ms": 262000, "data": {"id": "SHOCKZ", "attacker": {"means_of_death": "rifle_bullet", "id": "REPLAYS", "pos": {"y": 351, "x": 634}, "weapon": "BAR", "life": 91}, "pos": {"y": 366, "x": 533}, "life": 84}}, {"type": "spawn", "time_ms": 264050, "round": 1, "round_time_ms": 264050, "data": {"id": "SHOCKZ", "pos": {"y": 349, "x": 91}, "life": 92}}, {"type": "death", "time_ms": 264100, "round": 1, "round_time_ms": 264100, "data": {"id": "PRIESTAH", "attacker": {"means_of_death": "rifle_bullet", "id": "BUZZO", "pos": {"y": 377, "x": 405}, "weapon": "BAR", "life": 88}, "pos": {"y": 285, "x": 629}, "life": 85}}, {"type": "spawn", "time_ms": 266150, "round": 1, "round_time_ms": 266150, "data": {"id": "PRIESTAH", "pos": {"y": 499, "x": 892}, "life": 93}}, {"type": "death", "time_ms": 269500, "round": 1, "round_time_ms": 269500, "data": {"id": "DENZ", "attacker": {"means_of_death": "grenade_splash", "id": "ATTACH", "pos": {"y": 491, "x": 613}, "weapon": "Stielhandgranate", "life": 89}, "pos": {"y": 276, "x": 485}, "life": 90}}, {"type": "death", "time_ms": 271300, "round": 1, "round_time_ms": 271300, "data": {"id": "FIGHTA", "attacker": {"means_of_death": "head_shot", "id": "REPLAYS", "pos": {"y": 217, "x": 551}, "weapon": "BAR", "life": 91}, "pos": {"y": 244, "x": 484}, "life": 87}}, {"type": "spawn", "time_ms": 271550, "round": 1, "round_time_ms": 271550, "data": {"id": "DENZ", "pos": {"y": 349, "x": 91}, "life": 94}}, {"type": "death", "time_ms": 271700, "round": 1, "round_time_ms": 271700, "data": {"id": "REPLAYS", "attacker": {"means_of_death": "grenade_splash", "id": "SHOCKZ", "pos": {"y": 322, "x": 319}, "weapon": "No 74 ST", "life": 92}, "pos": {"y": 216, "x": 546}, "life": 91}}, {"type": "spawn", "time_ms": 273350, "round": 1, "round_time_ms": 273350, "data": {"id": "FIGHTA", "pos": {"y": 344, "x": 173}, "life": 95}}, {"type": "spawn", "time_ms": 273750, "round": 1, "round_time_ms": 273750, "data": {"id": "REPLAYS", "pos": {"y": 499, "x": 892}, "life": 96}}, {"type": "death", "time_ms": 276200, "round": 1, "round_time_ms": 276200, "data": {"id": "SHOCKZ", "attacker": {"means_of_death": "pistol_bullet", "id": "ZOOMAA", "pos": {"y": 221, "x": 550}, "weapon": "PPSh-41", "life": 86}, "pos": {"y": 266, "x": 410}, "life": 92}}, {"type": "spawn", "time_ms": 278250, "round": 1, "round_time_ms": 278250, "data": {"id": "SHOCKZ", "pos": {"y": 349, "x": 91}, "life": 97}}, {"type": "death", "time_ms": 278500, "round": 1, "round_time_ms": 278500, "data": {"id": "ATTACH", "attacker": {"means_of_death": "rifle_bullet", "id": "BUZZO", "pos": {"y": 547, "x": 605}, "weapon": "BAR", "life": 88}, "pos": {"y": 436, "x": 618}, "life": 89}}, {"type": "death", "time_ms": 280050, "round": 1, "round_time_ms": 280050, "data": {"id": "BUZZO", "attacker": {"means_of_death": "rifle_bullet", "id": "PRIESTAH", "pos": {"y": 372, "x": 611}, "weapon": "STG-44", "life": 93}, "pos": {"y": 549, "x": 623}, "life": 88}}, {"type": "spawn", "time_ms": 280550, "round": 1, "round_time_ms": 280550, "data": {"id": "ATTACH", "pos": {"y": 391, "x": 802}, "life": 98}}, {"type": "spawn", "time_ms": 282100, "round": 1, "round_time_ms": 282100, "data": {"id": "BUZZO", "pos": {"y": 349, "x": 91}, "life": 99}}, {"type": "death", "time_ms": 282300, "round": 1, "round_time_ms": 282300, "data": {"id": "ZOOMAA", "attacker": {"means_of_death": "head_shot", "id": "FIGHTA", "pos": {"y": 217, "x": 508}, "weapon": "PPSh-41", "life": 95}, "pos": {"y": 241, "x": 554}, "life": 86}}, {"type": "death", "time_ms": 283550, "round": 1, "round_time_ms": 283550, "data": {"id": "PRIESTAH", "attacker": {"means_of_death": "rifle_bullet", "id": "DENZ", "pos": {"y": 293, "x": 410}, "weapon": "STG-44", "life": 94}, "pos": {"y": 377, "x": 564}, "life": 93}}, {"type": "spawn", "time_ms": 284350, "round": 1, "round_time_ms": 284350, "data": {"id": "ZOOMAA", "pos": {"y": 499, "x": 892}, "life": 100}}, {"type": "spawn", "time_ms": 285600, "round": 1, "round_time_ms": 285600, "data": {"id": "PRIESTAH", "pos": {"y": 499, "x": 892}, "life": 101}}, {"type": "death", "time_ms": 291200, "round": 1, "round_time_ms": 291200, "data": {"id": "FIGHTA", "attacker": {"means_of_death": "pistol_bullet", "id": "ATTACH", "pos": {"y": 222, "x": 554}, "weapon": "PPSh-41", "life": 98}, "pos": {"y": 223, "x": 509}, "life": 95}}, {"type": "death", "time_ms": 293050, "round": 1, "round_time_ms": 293050, "data": {"id": "REPLAYS", "attacker": {"means_of_death": "head_shot", "id": "BUZZO", "pos": {"y": 559, "x": 378}, "weapon": "BAR", "life": 99}, "pos": {"y": 562, "x": 423}, "life": 96}}, {"type": "spawn", "time_ms": 293250, "round": 1, "round_time_ms": 293250, "data": {"id": "FIGHTA", "pos": {"y": 349, "x": 91}, "life": 102}}, {"type": "death", "time_ms": 293750, "round": 1, "round_time_ms": 293750, "data": {"id": "ATTACH", "attacker": {"means_of_death": "rifle_bullet", "id": "DENZ", "pos": {"y": 327, "x": 595}, "weapon": "STG-44", "life": 94}, "pos": {"y": 252, "x": 563}, "life": 98}}, {"type": "death", "time_ms": 294500, "round": 1, "round_time_ms": 294500, "data": {"id": "SHOCKZ", "attacker": {"means_of_death": "pistol_bullet", "id": "ZOOMAA", "pos": {"y": 520, "x": 462}, "weapon": "PPSh-41", "life": 100}, "pos": {"y": 471, "x": 454}, "life": 97}}, {"type": "spawn", "time_ms": 295100, "round": 1, "round_time_ms": 295100, "data": {"id": "REPLAYS", "pos": {"y": 660, "x": 881}, "life": 103}}, {"type": "spawn", "time_ms": 295800, "round": 1, "round_time_ms": 295800, "data": {"id": "ATTACH", "pos": {"y": 660, "x": 881}, "life": 104}}, {"type": "death", "time_ms": 296000, "round": 1, "round_time_ms": 296000, "data": {"id": "BUZZO", "attacker": {"means_of_death": "pistol_bullet", "id": "ZOOMAA", "pos": {"y": 544, "x": 467}, "weapon": "PPSh-41", "life": 100}, "pos": {"y": 572, "x": 426}, "life": 99}}, {"type": "spawn", "time_ms": 296550, "round": 1, "round_time_ms": 296550, "data": {"id": "SHOCKZ", "pos": {"y": 412, "x": 145}, "life": 105}}, {"type": "spawn", "time_ms": 298050, "round": 1, "round_time_ms": 298050, "data": {"id": "BUZZO", "pos": {"y": 344, "x": 173}, "life": 106}}, {"type": "death", "time_ms": 301700, "round": 1, "round_time_ms": 301700, "data": {"id": "ZOOMAA", "attacker": {"means_of_death": "pistol_bullet", "id": "SHOCKZ", "pos": {"y": 534, "x": 282}, "weapon": "PPSh-41", "life": 105}, "pos": {"y": 518, "x": 397}, "life": 100}}, {"type": "spawn", "time_ms": 303750, "round": 1, "round_time_ms": 303750, "data": {"id": "ZOOMAA", "pos": {"y": 499, "x": 892}, "life": 107}}, {"type": "death", "time_ms": 306950, "round": 1, "round_time_ms": 306950, "data": {"id": "SHOCKZ", "attacker": {"means_of_death": "rifle_bullet", "id": "PRIESTAH", "pos": {"y": 747, "x": 321}, "weapon": "STG-44", "life": 101}, "pos": {"y": 652, "x": 330}, "life": 105}}, {"type": "death", "time_ms": 308550, "round": 1, "round_time_ms": 308550, "data": {"id": "PRIESTAH", "attacker": {"means_of_death": "pistol_bullet", "id": "FIGHTA", "pos": {"y": 734, "x": 405}, "weapon": "PPSh-41", "life": 102}, "pos": {"y": 746, "x": 346}, "life": 101}}, {"type": "spawn", "time_ms": 309000, "round": 1, "round_time_ms": 309000, "data": {"id": "SHOCKZ", "pos": {"y": 320, "x": 311}, "life": 108}}, {"type": "death", "time_ms": 309950, "round": 1, "round_time_ms": 309950, "data": {"id": "FIGHTA", "attacker": {"means_of_death": "rifle_bullet", "id": "REPLAYS", "pos": {"y": 784, "x": 411}, "weapon": "BAR", "life": 103}, "pos": {"y": 765, "x": 409}, "life": 102}}, {"type": "spawn", "time_ms": 310600, "round": 1, "round_time_ms": 310600, "data": {"id": "PRIESTAH", "pos": {"y": 676, "x": 735}, "life": 109}}, {"type": "death", "time_ms": 310600, "round": 1, "round_time_ms": 310600, "data": {"id": "REPLAYS", "attacker": {"means_of_death": "rifle_bullet", "id": "BUZZO", "pos": {"y": 678, "x": 282}, "weapon": "BAR", "life": 106}, "pos": {"y": 782, "x": 424}, "life": 103}}, {"type": "spawn", "time_ms": 312000, "round": 1, "round_time_ms": 312000, "data": {"id": "FIGHTA", "pos": {"y": 425, "x": 243}, "life": 110}}, {"type": "spawn", "time_ms": 312650, "round": 1, "round_time_ms": 312650, "data": {"id": "REPLAYS", "pos": {"y": 667, "x": 918}, "life": 111}}, {"type": "death", "time_ms": 314750, "round": 1, "round_time_ms": 314750, "data": {"id": "BUZZO", "attacker": {"means_of_death": "pistol_bullet", "id": "ATTACH", "pos": {"y": 707, "x": 416}, "weapon": "PPSh-41", "life": 104}, "pos": {"y": 757, "x": 345}, "life": 106}}, {"type": "death", "time_ms": 317300, "round": 1, "round_time_ms": 317300, "data": {"id": "REPLAYS", "attacker": {"means_of_death": "rifle_bullet", "id": "DENZ", "pos": {"y": 487, "x": 707}, "weapon": "STG-44", "life": 94}, "pos": {"y": 656, "x": 739}, "life": 111}}, {"type": "spawn", "time_ms": 317550, "round": 1, "round_time_ms": 317550, "data": {"id": "BUZZO", "pos": {"y": 344, "x": 173}, "life": 112}}, {"type": "death", "time_ms": 318700, "round": 1, "round_time_ms": 318700, "data": {"id": "SHOCKZ", "attacker": {"means_of_death": "rifle_bullet", "id": "PRIESTAH", "pos": {"y": 634, "x": 553}, "weapon": "STG-44", "life": 109}, "pos": {"y": 570, "x": 464}, "life": 108}}, {"type": "spawn", "time_ms": 319350, "round": 1, "round_time_ms": 319350, "data": {"id": "REPLAYS", "pos": {"y": 667, "x": 918}, "life": 113}}, {"type": "spawn", "time_ms": 320750, "round": 1, "round_time_ms": 320750, "data": {"id": "SHOCKZ", "pos": {"y": 427, "x": 92}, "life": 114}}, {"type": "death", "time_ms": 323150, "round": 1, "round_time_ms": 323150, "data": {"id": "PRIESTAH", "attacker": {"means_of_death": "pistol_bullet", "id": "FIGHTA", "pos": {"y": 759, "x": 353}, "weapon": "PPSh-41", "life": 110}, "pos": {"y": 648, "x": 542}, "life": 109}}, {"type": "death", "time_ms": 323700, "round": 1, "round_time_ms": 323700, "data": {"id": "DENZ", "attacker": {"means_of_death": "head_shot", "id": "ZOOMAA", "pos": {"y": 747, "x": 495}, "weapon": "PPSh-41", "life": 107}, "pos": {"y": 586, "x": 522}, "life": 94}}, {"type": "death", "time_ms": 323900, "round": 1, "round_time_ms": 323900, "data": {"id": "FIGHTA", "attacker": {"means_of_death": "pistol_bullet", "id": "ATTACH", "pos": {"y": 691, "x": 454}, "weapon": "PPSh-41", "life": 104}, "pos": {"y": 760, "x": 349}, "life": 110}}, {"type": "spawn", "time_ms": 325200, "round": 1, "round_time_ms": 325200, "data": {"id": "PRIESTAH", "pos": {"y": 676, "x": 735}, "life": 115}}, {"type": "spawn", "time_ms": 325750, "round": 1, "round_time_ms": 325750, "data": {"id": "DENZ", "pos": {"y": 427, "x": 92}, "life": 116}}, {"type": "spawn", "time_ms": 325950, "round": 1, "round_time_ms": 325950, "data": {"id": "FIGHTA", "pos": {"y": 385, "x": 86}, "life": 117}}, {"type": "death", "time_ms": 337250, "round": 1, "round_time_ms": 337250, "data": {"id": "BUZZO", "attacker": {"means_of_death": "pistol_bullet", "id": "ATTACH", "pos": {"y": 580, "x": 500}, "weapon": "PPSh-41", "life": 104}, "pos": {"y": 564, "x": 405}, "life": 112}}, {"type": "death", "time_ms": 338750, "round": 1, "round_time_ms": 338750, "data": {"id": "ZOOMAA", "attacker": {"means_of_death": "rifle_bullet", "id": "DENZ", "pos": {"y": 715, "x": 343}, "weapon": "STG-44", "life": 116}, "pos": {"y": 762, "x": 427}, "life": 107}}, {"type": "spawn", "time_ms": 339300, "round": 1, "round_time_ms": 339300, "data": {"id": "BUZZO", "pos": {"y": 639, "x": 988}, "life": 118}}, {"type": "death", "time_ms": 339550, "round": 1, "round_time_ms": 339550, "data": {"id": "FIGHTA", "attacker": {"means_of_death": "pistol_bullet", "id": "ATTACH", "pos": {"y": 632, "x": 474}, "weapon": "PPSh-41", "life": 104}, "pos": {"y": 718, "x": 487}, "life": 117}}, {"type": "death", "time_ms": 340300, "round": 1, "round_time_ms": 340300, "data": {"id": "DENZ", "attacker": {"means_of_death": "rifle_bullet", "id": "REPLAYS", "pos": {"y": 747, "x": 539}, "weapon": "BAR", "life": 113}, "pos": {"y": 718, "x": 348}, "life": 116}}, {"type": "spawn", "time_ms": 340800, "round": 1, "round_time_ms": 340800, "data": {"id": "ZOOMAA", "pos": {"y": 417, "x": 670}, "life": 119}}, {"type": "spawn", "time_ms": 341600, "round": 1, "round_time_ms": 341600, "data": {"id": "FIGHTA", "pos": {"y": 655, "x": 982}, "life": 120}}, {"type": "spawn", "time_ms": 342350, "round": 1, "round_time_ms": 342350, "data": {"id": "DENZ", "pos": {"y": 655, "x": 982}, "life": 121}}, {"type": "death", "time_ms": 354200, "round": 1, "round_time_ms": 354200, "data": {"id": "SHOCKZ", "attacker": {"means_of_death": "pistol_bullet", "id": "ATTACH", "pos": {"y": 573, "x": 238}, "weapon": "PPSh-41", "life": 104}, "pos": {"y": 646, "x": 344}, "life": 114}}, {"type": "spawn", "time_ms": 356250, "round": 1, "round_time_ms": 356250, "data": {"id": "SHOCKZ", "pos": {"y": 547, "x": 895}, "life": 122}}, {"type": "death", "time_ms": 362000, "round": 1, "round_time_ms": 362000, "data": {"id": "PRIESTAH", "attacker": {"means_of_death": "pistol_bullet", "id": "FIGHTA", "pos": {"y": 312, "x": 385}, "weapon": "PPSh-41", "life": 120}, "pos": {"y": 392, "x": 407}, "life": 115}}, {"type": "death", "time_ms": 363350, "round": 1, "round_time_ms": 363350, "data": {"id": "FIGHTA", "attacker": {"means_of_death": "pistol_bullet", "id": "ATTACH", "pos": {"y": 354, "x": 345}, "weapon": "PPSh-41", "life": 104}, "pos": {"y": 316, "x": 402}, "life": 120}}, {"type": "death", "time_ms": 364250, "round": 1, "round_time_ms": 364250, "data": {"id": "BUZZO", "attacker": {"means_of_death": "head_shot", "id": "ZOOMAA", "pos": {"y": 255, "x": 358}, "weapon": "PPSh-41", "life": 119}, "pos": {"y": 305, "x": 474}, "life": 118}}, {"type": "spawn", "time_ms": 364650, "round": 1, "round_time_ms": 364650, "data": {"id": "PRIESTAH", "pos": {"y": 689, "x": 296}, "life": 123}}, {"type": "spawn", "time_ms": 365400, "round": 1, "round_time_ms": 365400, "data": {"id": "FIGHTA", "pos": {"y": 499, "x": 892}, "life": 124}}, {"type": "death", "time_ms": 365900, "round": 1, "round_time_ms": 365900, "data": {"id": "ZOOMAA", "attacker": {"means_of_death": "head_shot", "id": "DENZ", "pos": {"y": 382, "x": 570}, "weapon": "STG-44", "life": 121}, "pos": {"y": 275, "x": 404}, "life": 119}}, {"type": "spawn", "time_ms": 366300, "round": 1, "round_time_ms": 366300, "data": {"id": "BUZZO", "pos": {"y": 499, "x": 892}, "life": 125}}, {"type": "spawn", "time_ms": 367950, "round": 1, "round_time_ms": 367950, "data": {"id": "ZOOMAA", "pos": {"y": 657, "x": 272}, "life": 126}}, {"type": "death", "time_ms": 376500, "round": 1, "round_time_ms": 376500, "data": {"id": "PRIESTAH", "attacker": {"means_of_death": "pistol_bullet", "id": "SHOCKZ", "pos": {"y": 295, "x": 392}, "weapon": "PPSh-41", "life": 122}, "pos": {"y": 348, "x": 261}, "life": 123}}, {"type": "death", "time_ms": 377050, "round": 1, "round_time_ms": 377050, "data": {"id": "FIGHTA", "attacker": {"means_of_death": "rifle_bullet", "id": "REPLAYS", "pos": {"y": 592, "x": 510}, "weapon": "BAR", "life": 113}, "pos": {"y": 549, "x": 509}, "life": 124}}, {"type": "spawn", "time_ms": 378550, "round": 1, "round_time_ms": 378550, "data": {"id": "PRIESTAH", "pos": {"y": 748, "x": 328}, "life": 127}}, {"type": "death", "time_ms": 378650, "round": 1, "round_time_ms": 378650, "data": {"id": "ZOOMAA", "attacker": {"means_of_death": "rifle_bullet", "id": "DENZ", "pos": {"y": 330, "x": 363}, "weapon": "STG-44", "life": 121}, "pos": {"y": 379, "x": 334}, "life": 126}}, {"type": "death", "time_ms": 378850, "round": 1, "round_time_ms": 378850, "data": {"id": "DENZ", "attacker": {"means_of_death": "pistol_bullet", "id": "ATTACH", "pos": {"y": 364, "x": 318}, "weapon": "PPSh-41", "life": 104}, "pos": {"y": 331, "x": 360}, "life": 121}}, {"type": "spawn", "time_ms": 379100, "round": 1, "round_time_ms": 379100, "data": {"id": "FIGHTA", "pos": {"y": 391, "x": 802}, "life": 128}}, {"type": "spawn", "time_ms": 380700, "round": 1, "round_time_ms": 380700, "data": {"id": "ZOOMAA", "pos": {"y": 716, "x": 312}, "life": 129}}, {"type": "spawn", "time_ms": 380900, "round": 1, "round_time_ms": 380900, "data": {"id": "DENZ", "pos": {"y": 391, "x": 802}, "life": 130}}, {"type": "death", "time_ms": 381750, "round": 1, "round_time_ms": 381750, "data": {"id": "ATTACH", "attacker": {"means_of_death": "pistol_bullet", "id": "SHOCKZ", "pos": {"y": 317, "x": 400}, "weapon": "PPSh-41", "life": 122}, "pos": {"y": 332, "x": 375}, "life": 104}}, {"type": "death", "time_ms": 383400, "round": 1, "round_time_ms": 383400, "data": {"id": "REPLAYS", "attacker": {"means_of_death": "pistol_bullet", "id": "FIGHTA", "pos": {"y": 429, "x": 625}, "weapon": "PPSh-41", "life": 128}, "pos": {"y": 431, "x": 616}, "life": 113}}, {"type": "spawn", "time_ms": 383800, "round": 1, "round_time_ms": 383800, "data": {"id": "ATTACH", "pos": {"y": 657, "x": 272}, "life": 131}}, {"type": "spawn", "time_ms": 385450, "round": 1, "round_time_ms": 385450, "data": {"id": "REPLAYS", "pos": {"y": 748, "x": 328}, "life": 132}}, {"type": "death", "time_ms": 385850, "round": 1, "round_time_ms": 385850, "data": {"id": "SHOCKZ", "attacker": {"means_of_death": "rifle_bullet", "id": "PRIESTAH", "pos": {"y": 521, "x": 230}, "weapon": "STG-44", "life": 127}, "pos": {"y": 311, "x": 319}, "life": 122}}, {"type": "spawn", "time_ms": 387900, "round": 1, "round_time_ms": 387900, "data": {"id": "SHOCKZ", "pos": {"y": 304, "x": 713}, "life": 133}}, {"type": "death", "time_ms": 389100, "round": 1, "round_time_ms": 389100, "data": {"id": "PRIESTAH", "attacker": {"means_of_death": "rifle_bullet", "id": "BUZZO", "pos": {"y": 334, "x": 351}, "weapon": "BAR", "life": 125}, "pos": {"y": 449, "x": 210}, "life": 127}}, {"type": "death", "time_ms": 391050, "round": 1, "round_time_ms": 391050, "data": {"id": "FIGHTA", "attacker": {"means_of_death": "projectile_splash", "id": "ATTACH", "pos": {"y": 459, "x": 270}, "weapon": "Artillery Barrage", "life": 131}, "pos": {"y": 357, "x": 491}, "life": 128}}, {"type": "spawn", "time_ms": 391150, "round": 1, "round_time_ms": 391150, "data": {"id": "PRIESTAH", "pos": {"y": 748, "x": 328}, "life": 134}}, {"type": "spawn", "time_ms": 393100, "round": 1, "round_time_ms": 393100, "data": {"id": "FIGHTA", "pos": {"y": 304, "x": 713}, "life": 135}}, {"type": "death", "time_ms": 394600, "round": 1, "round_time_ms": 394600, "data": {"id": "ATTACH", "attacker": {"means_of_death": "rifle_bullet", "id": "DENZ", "pos": {"y": 258, "x": 348}, "weapon": "STG-44", "life": 130}, "pos": {"y": 397, "x": 275}, "life": 131}}, {"type": "death", "time_ms": 395000, "round": 1, "round_time_ms": 395000, "data": {"id": "BUZZO", "attacker": {"means_of_death": "grenade_splash", "id": "ATTACH", "pos": {"y": 397, "x": 267}, "weapon": "Stielhandgranate", "life": 131}, "pos": {"y": 365, "x": 317}, "life": 125}}, {"type": "death", "time_ms": 395750, "round": 1, "round_time_ms": 395750, "data": {"id": "ZOOMAA", "attacker": {"means_of_death": "rifle_bullet", "id": "DENZ", "pos": {"y": 262, "x": 350}, "weapon": "STG-44", "life": 130}, "pos": {"y": 419, "x": 260}, "life": 129}}, {"type": "spawn", "time_ms": 396650, "round": 1, "round_time_ms": 396650, "data": {"id": "ATTACH", "pos": {"y": 748, "x": 328}, "life": 136}}, {"type": "spawn", "time_ms": 397050, "round": 1, "round_time_ms": 397050, "data": {"id": "BUZZO", "pos": {"y": 304, "x": 713}, "life": 137}}, {"type": "death", "time_ms": 397050, "round": 1, "round_time_ms": 397050, "data": {"id": "REPLAYS", "attacker": {"means_of_death": "pistol_bullet", "id": "SHOCKZ", "pos": {"y": 237, "x": 477}, "weapon": "PPSh-41", "life": 133}, "pos": {"y": 505, "x": 463}, "life": 132}}, {"type": "spawn", "time_ms": 397800, "round": 1, "round_time_ms": 397800, "data": {"id": "ZOOMAA", "pos": {"y": 748, "x": 328}, "life": 138}}, {"type": "death", "time_ms": 398500, "round": 1, "round_time_ms": 398500, "data": {"id": "FIGHTA", "attacker": {"means_of_death": "projectile_splash", "id": "ATTACH", "pos": {"y": 678, "x": 340}, "weapon": "Artillery Barrage", "life": 136}, "pos": {"y": 369, "x": 482}, "life": 135}}, {"type": "spawn", "time_ms": 399100, "round": 1, "round_time_ms": 399100, "data": {"id": "REPLAYS", "pos": {"y": 748, "x": 328}, "life": 139}}, {"type": "death", "time_ms": 399700, "round": 1, "round_time_ms": 399700, "data": {"id": "DENZ", "attacker": {"means_of_death": "rifle_bullet", "id": "PRIESTAH", "pos": {"y": 468, "x": 249}, "weapon": "STG-44", "life": 134}, "pos": {"y": 296, "x": 332}, "life": 130}}, {"type": "spawn", "time_ms": 400550, "round": 1, "round_time_ms": 400550, "data": {"id": "FIGHTA", "pos": {"y": 304, "x": 713}, "life": 140}}, {"type": "spawn", "time_ms": 401750, "round": 1, "round_time_ms": 401750, "data": {"id": "DENZ", "pos": {"y": 304, "x": 713}, "life": 141}}, {"type": "death", "time_ms": 402300, "round": 1, "round_time_ms": 402300, "data": {"id": "SHOCKZ", "attacker": {"means_of_death": "rifle_bullet", "id": "PRIESTAH", "pos": {"y": 410, "x": 259}, "weapon": "STG-44", "life": 134}, "pos": {"y": 306, "x": 337}, "life": 133}}, {"type": "spawn", "time_ms": 404350, "round": 1, "round_time_ms": 404350, "data": {"id": "SHOCKZ", "pos": {"y": 391, "x": 802}, "life": 142}}, {"type": "death", "time_ms": 408200, "round": 1, "round_time_ms": 408200, "data": {"id": "FIGHTA", "attacker": {"means_of_death": "pistol_bullet", "id": "ZOOMAA", "pos": {"y": 453, "x": 475}, "weapon": "PPSh-41", "life": 138}, "pos": {"y": 359, "x": 426}, "life": 140}}, {"type": "death", "time_ms": 409250, "round": 1, "round_time_ms": 409250, "data": {"id": "DENZ", "attacker": {"means_of_death": "rifle_bullet", "id": "REPLAYS", "pos": {"y": 540, "x": 598}, "weapon": "BAR", "life": 139}, "pos": {"y": 499, "x": 602}, "life": 141}}, {"type": "spawn", "time_ms": 410250, "round": 1, "round_time_ms": 410250, "data": {"id": "FIGHTA", "pos": {"y": 547, "x": 895}, "life": 143}}, {"type": "spawn", "time_ms": 411300, "round": 1, "round_time_ms": 411300, "data": {"id": "DENZ", "pos": {"y": 547, "x": 895}, "life": 144}}, {"type": "death", "time_ms": 412900, "round": 1, "round_time_ms": 412900, "data": {"id": "SHOCKZ", "attacker": {"means_of_death": "pistol_bullet", "id": "ZOOMAA", "pos": {"y": 460, "x": 454}, "weapon": "PPSh-41", "life": 138}, "pos": {"y": 383, "x": 475}, "life": 142}}, {"type": "death", "time_ms": 413550, "round": 1, "round_time_ms": 413550, "data": {"id": "ATTACH", "attacker": {"means_of_death": "rifle_bullet", "id": "BUZZO", "pos": {"y": 393, "x": 408}, "weapon": "BAR", "life": 137}, "pos": {"y": 333, "x": 392}, "life": 136}}, {"type": "death", "time_ms": 414500, "round": 1, "round_time_ms": 414500, "data": {"id": "BUZZO", "attacker": {"means_of_death": "pistol_bullet", "id": "PRIESTAH", "pos": {"y": 330, "x": 367}, "weapon": "PPSh-41", "life": 134}, "pos": {"y": 395, "x": 408}, "life": 137}}, {"type": "spawn", "time_ms": 414950, "round": 1, "round_time_ms": 414950, "data": {"id": "SHOCKZ", "pos": {"y": 385, "x": 86}, "life": 145}}, {"type": "death", "time_ms": 415500, "round": 1, "round_time_ms": 415500, "data": {"id": "FIGHTA", "attacker": {"means_of_death": "rifle_bullet", "id": "REPLAYS", "pos": {"y": 480, "x": 652}, "weapon": "BAR", "life": 139}, "pos": {"y": 481, "x": 683}, "life": 143}}, {"type": "spawn", "time_ms": 415600, "round": 1, "round_time_ms": 415600, "data": {"id": "ATTACH", "pos": {"y": 748, "x": 328}, "life": 146}}, {"type": "death", "time_ms": 415700, "round": 1, "round_time_ms": 415700, "data": {"id": "REPLAYS", "attacker": {"means_of_death": "rifle_bullet", "id": "DENZ", "pos": {"y": 503, "x": 753}, "weapon": "STG-44", "life": 144}, "pos": {"y": 480, "x": 652}, "life": 139}}, {"type": "spawn", "time_ms": 416550, "round": 1, "round_time_ms": 416550, "data": {"id": "BUZZO", "pos": {"y": 533, "x": 824}, "life": 147}}, {"type": "spawn", "time_ms": 417550, "round": 1, "round_time_ms": 417550, "data": {"id": "FIGHTA", "pos": {"y": 533, "x": 824}, "life": 148}}, {"type": "spawn", "time_ms": 417750, "round": 1, "round_time_ms": 417750, "data": {"id": "REPLAYS", "pos": {"y": 304, "x": 713}, "life": 149}}, {"type": "death", "time_ms": 418750, "round": 1, "round_time_ms": 418750, "data": {"id": "ZOOMAA", "attacker": {"means_of_death": "head_shot", "id": "SHOCKZ", "pos": {"y": 451, "x": 208}, "weapon": "PPSh-41", "life": 145}, "pos": {"y": 554, "x": 410}, "life": 138}}, {"type": "spawn", "time_ms": 420800, "round": 1, "round_time_ms": 420800, "data": {"id": "ZOOMAA", "pos": {"y": 748, "x": 328}, "life": 150}}, {"type": "death", "time_ms": 425550, "round": 1, "round_time_ms": 425550, "data": {"id": "ATTACH", "attacker": {"means_of_death": "rifle_bullet", "id": "DENZ", "pos": {"y": 628, "x": 618}, "weapon": "STG-44", "life": 144}, "pos": {"y": 632, "x": 595}, "life": 146}}, {"type": "death", "time_ms": 425600, "round": 1, "round_time_ms": 425600, "data": {"id": "REPLAYS", "attacker": {"means_of_death": "pistol_bullet", "id": "FIGHTA", "pos": {"y": 288, "x": 704}, "weapon": "PPSh-41", "life": 148}, "pos": {"y": 276, "x": 607}, "life": 149}}, {"type": "spawn", "time_ms": 427600, "round": 1, "round_time_ms": 427600, "data": {"id": "ATTACH", "pos": {"y": 603, "x": 268}, "life": 151}}, {"type": "spawn", "time_ms": 427650, "round": 1, "round_time_ms": 427650, "data": {"id": "REPLAYS", "pos": {"y": 657, "x": 272}, "life": 152}}, {"type": "death", "time_ms": 431550, "round": 1, "round_time_ms": 431550, "data": {"id": "ATTACH", "attacker": {"means_of_death": "pistol_bullet", "id": "SHOCKZ", "pos": {"y": 559, "x": 431}, "weapon": "PPSh-41", "life": 145}, "pos": {"y": 528, "x": 357}, "life": 151}}, {"type": "death", "time_ms": 432400, "round": 1, "round_time_ms": 432400, "data": {"id": "REPLAYS", "attacker": {"means_of_death": "rifle_bullet", "id": "DENZ", "pos": {"y": 652, "x": 540}, "weapon": "STG-44", "life": 144}, "pos": {"y": 714, "x": 423}, "life": 152}}, {"type": "spawn", "time_ms": 433600, "round": 1, "round_time_ms": 433600, "data": {"id": "ATTACH", "pos": {"y": 349, "x": 91}, "life": 153}}, {"type": "death", "time_ms": 433650, "round": 1, "round_time_ms": 433650, "data": {"id": "SHOCKZ", "attacker": {"means_of_death": "pistol_bullet", "id": "ZOOMAA", "pos": {"y": 590, "x": 510}, "weapon": "PPSh-41", "life": 150}, "pos": {"y": 547, "x": 458}, "life": 145}}, {"type": "death", "time_ms": 434400, "round": 1, "round_time_ms": 434400, "data": {"id": "ZOOMAA", "attacker": {"means_of_death": "rifle_bullet", "id": "DENZ", "pos": {"y": 626, "x": 548}, "weapon": "STG-44", "life": 144}, "pos": {"y": 605, "x": 490}, "life": 150}}, {"type": "spawn", "time_ms": 434450, "round": 1, "round_time_ms": 434450, "data": {"id": "REPLAYS", "pos": {"y": 344, "x": 173}, "life": 154}}, {"type": "spawn", "time_ms": 435700, "round": 1, "round_time_ms": 435700, "data": {"id": "SHOCKZ", "pos": {"y": 646, "x": 839}, "life": 155}}, {"type": "spawn", "time_ms": 436450, "round": 1, "round_time_ms": 436450, "data": {"id": "ZOOMAA", "pos": {"y": 356, "x": 219}, "life": 156}}, {"type": "death", "time_ms": 444900, "round": 1, "round_time_ms": 444900, "data": {"id": "SHOCKZ", "attacker": {"means_of_death": "pistol_bullet", "id": "ZOOMAA", "pos": {"y": 362, "x": 547}, "weapon": "PPSh-41", "life": 156}, "pos": {"y": 425, "x": 653}, "life": 155}}, {"type": "death", "time_ms": 445000, "round": 1, "round_time_ms": 445000, "data": {"id": "DENZ", "attacker": {"means_of_death": "explosive_bullet", "id": "ATTACH", "pos": {"y": 349, "x": 232}, "weapon": "Fighter Pilot", "life": 153}, "pos": {"y": 642, "x": 475}, "life": 144}}, {"type": "death", "time_ms": 446650, "round": 1, "round_time_ms": 446650, "data": {"id": "ZOOMAA", "attacker": {"means_of_death": "grenade_splash", "id": "SHOCKZ", "pos": {"y": 424, "x": 654}, "weapon": "No 74 ST", "life": 155}, "pos": {"y": 406, "x": 614}, "life": 156}}, {"type": "spawn", "time_ms": 446950, "round": 1, "round_time_ms": 446950, "data": {"id": "SHOCKZ", "pos": {"y": 639, "x": 988}, "life": 157}}, {"type": "spawn", "time_ms": 447000, "round": 1, "round_time_ms": 447000, "data": {"id": "DENZ", "pos": {"y": 627, "x": 984}, "life": 158}}, {"type": "spawn", "time_ms": 448700, "round": 1, "round_time_ms": 448700, "data": {"id": "ZOOMAA", "pos": {"y": 716, "x": 312}, "life": 159}}, {"type": "death", "time_ms": 449800, "round": 1, "round_time_ms": 449800, "data": {"id": "FIGHTA", "attacker": {"means_of_death": "pistol_bullet", "id": "PRIESTAH", "pos": {"y": 536, "x": 636}, "weapon": "PPSh-41", "life": 134}, "pos": {"y": 429, "x": 601}, "life": 148}}, {"type": "spawn", "time_ms": 451850, "round": 1, "round_time_ms": 451850, "data": {"id": "FIGHTA", "pos": {"y": 547, "x": 895}, "life": 160}}, {"type": "death", "time_ms": 452200, "round": 1, "round_time_ms": 452200, "data": {"id": "PRIESTAH", "attacker": {"means_of_death": "grenade_splash", "id": "SHOCKZ", "pos": {"y": 522, "x": 806}, "weapon": "No 74 ST", "life": 157}, "pos": {"y": 549, "x": 594}, "life": 134}}, {"type": "death", "time_ms": 452200, "round": 1, "round_time_ms": 452200, "data": {"id": "REPLAYS", "attacker": {"means_of_death": "rifle_bullet", "id": "BUZZO", "pos": {"y": 329, "x": 643}, "weapon": "BAR", "life": 147}, "pos": {"y": 308, "x": 516}, "life": 154}}, {"type": "spawn", "time_ms": 454250, "round": 1, "round_time_ms": 454250, "data": {"id": "PRIESTAH", "pos": {"y": 657, "x": 272}, "life": 161}}, {"type": "spawn", "time_ms": 455300, "round": 1, "round_time_ms": 455300, "data": {"id": "REPLAYS", "pos": {"y": 689, "x": 296}, "life": 162}}, {"type": "death", "time_ms": 456350, "round": 1, "round_time_ms": 456350, "data": {"id": "DENZ", "attacker": {"means_of_death": "grenade_splash", "id": "ATTACH", "pos": {"y": 518, "x": 482}, "weapon": "Stielhandgranate", "life": 153}, "pos": {"y": 502, "x": 720}, "life": 158}}, {"type": "spawn", "time_ms": 458400, "round": 1, "round_time_ms": 458400, "data": {"id": "DENZ", "pos": {"y": 627, "x": 984}, "life": 163}}, {"type": "death", "time_ms": 459100, "round": 1, "round_time_ms": 459100, "data": {"id": "ATTACH", "attacker": {"means_of_death": "rifle_bullet", "id": "BUZZO", "pos": {"y": 416, "x": 466}, "weapon": "BAR", "life": 147}, "pos": {"y": 475, "x": 459}, "life": 153}}, {"type": "death", "time_ms": 460300, "round": 1, "round_time_ms": 460300, "data": {"id": "SHOCKZ", "attacker": {"means_of_death": "explosive_bullet", "id": "PRIESTAH", "pos": {"y": 657, "x": 272}, "weapon": "Fighter Pilot", "life": 161}, "pos": {"y": 542, "x": 596}, "life": 157}}, {"type": "spawn", "time_ms": 461150, "round": 1, "round_time_ms": 461150, "data": {"id": "ATTACH", "pos": {"y": 689, "x": 296}, "life": 164}}, {"type": "death", "time_ms": 461350, "round": 1, "round_time_ms": 461350, "data": {"id": "BUZZO", "attacker": {"means_of_death": "explosive_bullet", "id": "PRIESTAH", "pos": {"y": 657, "x": 272}, "weapon": "Fighter Pilot", "life": 161}, "pos": {"y": 367, "x": 514}, "life": 147}}, {"type": "spawn", "time_ms": 462300, "round": 1, "round_time_ms": 462300, "data": {"id": "SHOCKZ", "pos": {"y": 217, "x": 392}, "life": 165}}, {"type": "spawn", "time_ms": 463350, "round": 1, "round_time_ms": 463350, "data": {"id": "BUZZO", "pos": {"y": 217, "x": 392}, "life": 166}}, {"type": "death", "time_ms": 466200, "round": 1, "round_time_ms": 466200, "data": {"id": "FIGHTA", "attacker": {"means_of_death": "pistol_bullet", "id": "ZOOMAA", "pos": {"y": 454, "x": 624}, "weapon": "PPSh-41", "life": 159}, "pos": {"y": 416, "x": 634}, "life": 160}}, {"type": "spawn", "time_ms": 468250, "round": 1, "round_time_ms": 468250, "data": {"id": "FIGHTA", "pos": {"y": 655, "x": 982}, "life": 167}}, {"type": "death", "time_ms": 469000, "round": 1, "round_time_ms": 469000, "data": {"id": "BUZZO", "attacker": {"means_of_death": "pistol_bullet", "id": "ZOOMAA", "pos": {"y": 372, "x": 644}, "weapon": "PPSh-41", "life": 159}, "pos": {"y": 315, "x": 552}, "life": 166}}, {"type": "death", "time_ms": 471000, "round": 1, "round_time_ms": 471000, "data": {"id": "ZOOMAA", "attacker": {"means_of_death": "pistol_bullet", "id": "SHOCKZ", "pos": {"y": 339, "x": 591}, "weapon": "PPSh-41", "life": 165}, "pos": {"y": 366, "x": 643}, "life": 159}}, {"type": "spawn", "time_ms": 471050, "round": 1, "round_time_ms": 471050, "data": {"id": "BUZZO", "pos": {"y": 604, "x": 972}, "life": 168}}, {"type": "spawn", "time_ms": 473050, "round": 1, "round_time_ms": 473050, "data": {"id": "ZOOMAA", "pos": {"y": 428, "x": 185}, "life": 169}}, {"type": "death", "time_ms": 475800, "round": 1, "round_time_ms": 475800, "data": {"id": "PRIESTAH", "attacker": {"means_of_death": "rifle_bullet", "id": "DENZ", "pos": {"y": 635, "x": 543}, "weapon": "STG-44", "life": 163}, "pos": {"y": 537, "x": 506}, "life": 161}}, {"type": "death", "time_ms": 477000, "round": 1, "round_time_ms": 477000, "data": {"id": "FIGHTA", "attacker": {"means_of_death": "pistol_bullet", "id": "ATTACH", "pos": {"y": 537, "x": 571}, "weapon": "PPSh-41", "life": 164}, "pos": {"y": 482, "x": 662}, "life": 167}}, {"type": "death", "time_ms": 477800, "round": 1, "round_time_ms": 477800, "data": {"id": "REPLAYS", "attacker": {"means_of_death": "head_shot", "id": "SHOCKZ", "pos": {"y": 269, "x": 586}, "weapon": "PPSh-41", "life": 165}, "pos": {"y": 547, "x": 618}, "life": 162}}, {"type": "spawn", "time_ms": 477850, "round": 1, "round_time_ms": 477850, "data": {"id": "PRIESTAH", "pos": {"y": 349, "x": 91}, "life": 170}}, {"type": "death", "time_ms": 478600, "round": 1, "round_time_ms": 478600, "data": {"id": "ATTACH", "attacker": {"means_of_death": "rifle_bullet", "id": "DENZ", "pos": {"y": 584, "x": 494}, "weapon": "STG-44", "life": 163}, "pos": {"y": 543, "x": 536}, "life": 164}}, {"type": "spawn", "time_ms": 479050, "round": 1, "round_time_ms": 479050, "data": {"id": "FIGHTA", "pos": {"y": 499, "x": 892}, "life": 171}}, {"type": "spawn", "time_ms": 479850, "round": 1, "round_time_ms": 479850, "data": {"id": "REPLAYS", "pos": {"y": 344, "x": 173}, "life": 172}}, {"type": "spawn", "time_ms": 480650, "round": 1, "round_time_ms": 480650, "data": {"id": "ATTACH", "pos": {"y": 344, "x": 173}, "life": 173}}, {"type": "death", "time_ms": 481900, "round": 1, "round_time_ms": 481900, "data": {"id": "DENZ", "attacker": {"means_of_death": "pistol_bullet", "id": "ZOOMAA", "pos": {"y": 498, "x": 459}, "weapon": "PPSh-41", "life": 169}, "pos": {"y": 608, "x": 505}, "life": 163}}, {"type": "spawn", "time_ms": 483950, "round": 1, "round_time_ms": 483950, "data": {"id": "DENZ", "pos": {"y": 667, "x": 918}, "life": 174}}, {"type": "death", "time_ms": 484000, "round": 1, "round_time_ms": 484000, "data": {"id": "SHOCKZ", "attacker": {"means_of_death": "rifle_bullet", "id": "PRIESTAH", "pos": {"y": 300, "x": 302}, "weapon": "STG-44", "life": 170}, "pos": {"y": 323, "x": 460}, "life": 165}}, {"type": "death", "time_ms": 485800, "round": 1, "round_time_ms": 485800, "data": {"id": "ZOOMAA", "attacker": {"means_of_death": "grenade_splash", "id": "FIGHTA", "pos": {"y": 502, "x": 632}, "weapon": "No 74 ST", "life": 171}, "pos": {"y": 511, "x": 476}, "life": 169}}, {"type": "spawn", "time_ms": 486050, "round": 1, "round_time_ms": 486050, "data": {"id": "SHOCKZ", "pos": {"y": 626, "x": 853}, "life": 175}}, {"type": "spawn", "time_ms": 487850, "round": 1, "round_time_ms": 487850, "data": {"id": "ZOOMAA", "pos": {"y": 412, "x": 145}, "life": 176}}, {"type": "death", "time_ms": 488650, "round": 1, "round_time_ms": 488650, "data": {"id": "BUZZO", "attacker": {"means_of_death": "rifle_bullet", "id": "PRIESTAH", "pos": {"y": 232, "x": 389}, "weapon": "STG-44", "life": 170}, "pos": {"y": 421, "x": 618}, "life": 168}}, {"type": "spawn", "time_ms": 490700, "round": 1, "round_time_ms": 490700, "data": {"id": "BUZZO", "pos": {"y": 499, "x": 892}, "life": 177}}, {"type": "death", "time_ms": 494100, "round": 1, "round_time_ms": 494100, "data": {"id": "FIGHTA", "attacker": {"means_of_death": "rifle_bullet", "id": "REPLAYS", "pos": {"y": 559, "x": 409}, "weapon": "STG-44", "life": 172}, "pos": {"y": 489, "x": 609}, "life": 171}}, {"type": "spawn", "time_ms": 496150, "round": 1, "round_time_ms": 496150, "data": {"id": "FIGHTA", "pos": {"y": 499, "x": 892}, "life": 178}}, {"type": "death", "time_ms": 496750, "round": 1, "round_time_ms": 496750, "data": {"id": "SHOCKZ", "attacker": {"means_of_death": "rifle_bullet", "id": "REPLAYS", "pos": {"y": 554, "x": 408}, "weapon": "STG-44", "life": 172}, "pos": {"y": 528, "x": 590}, "life": 175}}, {"type": "spawn", "time_ms": 498800, "round": 1, "round_time_ms": 498800, "data": {"id": "SHOCKZ", "pos": {"y": 499, "x": 892}, "life": 179}}, {"type": "death", "time_ms": 502050, "round": 1, "round_time_ms": 502050, "data": {"id": "FIGHTA", "attacker": {"means_of_death": "rifle_bullet", "id": "REPLAYS", "pos": {"y": 562, "x": 527}, "weapon": "STG-44", "life": 172}, "pos": {"y": 487, "x": 664}, "life": 178}}, {"type": "death", "time_ms": 502850, "round": 1, "round_time_ms": 502850, "data": {"id": "BUZZO", "attacker": {"means_of_death": "projectile_splash", "id": "PRIESTAH", "pos": {"y": 246, "x": 488}, "weapon": "Glide Bomb", "life": 134}, "pos": {"y": 299, "x": 636}, "life": 177}}, {"type": "spawn", "time_ms": 504100, "round": 1, "round_time_ms": 504100, "data": {"id": "FIGHTA", "pos": {"y": 604, "x": 972}, "life": 180}}, {"type": "spawn", "time_ms": 505100, "round": 1, "round_time_ms": 505100, "data": {"id": "BUZZO", "pos": {"y": 604, "x": 972}, "life": 181}}, {"type": "death", "time_ms": 505450, "round": 1, "round_time_ms": 505450, "data": {"id": "ZOOMAA", "attacker": {"means_of_death": "rifle_bullet", "id": "DENZ", "pos": {"y": 476, "x": 609}, "weapon": "STG-44", "life": 174}, "pos": {"y": 531, "x": 539}, "life": 176}}, {"type": "spawn", "time_ms": 507500, "round": 1, "round_time_ms": 507500, "data": {"id": "ZOOMAA", "pos": {"y": 344, "x": 173}, "life": 182}}, {"type": "death", "time_ms": 508400, "round": 1, "round_time_ms": 508400, "data": {"id": "DENZ", "attacker": {"means_of_death": "projectile_splash", "id": "ATTACH", "pos": {"y": 430, "x": 460}, "weapon": "Glide Bomb", "life": 104}, "pos": {"y": 491, "x": 551}, "life": 174}}, {"type": "death", "time_ms": 508400, "round": 1, "round_time_ms": 508400, "data": {"id": "SHOCKZ", "attacker": {"means_of_death": "projectile_splash", "id": "ATTACH", "pos": {"y": 430, "x": 460}, "weapon": "Glide Bomb", "life": 104}, "pos": {"y": 434, "x": 603}, "life": 179}}, {"type": "spawn", "time_ms": 510450, "round": 1, "round_time_ms": 510450, "data": {"id": "DENZ", "pos": {"y": 499, "x": 892}, "life": 183}}, {"type": "spawn", "time_ms": 510500, "round": 1, "round_time_ms": 510500, "data": {"id": "SHOCKZ", "pos": {"y": 547, "x": 895}, "life": 184}}, {"type": "death", "time_ms": 517150, "round": 1, "round_time_ms": 517150, "data": {"id": "REPLAYS", "attacker": {"means_of_death": "grenade_splash", "id": "SHOCKZ", "pos": {"y": 494, "x": 668}, "weapon": "Mk2 Frag Grenade", "life": 184}, "pos": {"y": 519, "x": 539}, "life": 172}}, {"type": "spawn", "time_ms": 519200, "round": 1, "round_time_ms": 519200, "data": {"id": "REPLAYS", "pos": {"y": 349, "x": 91}, "life": 185}}, {"type": "death", "time_ms": 519750, "round": 1, "round_time_ms": 519750, "data": {"id": "PRIESTAH", "attacker": {"means_of_death": "rifle_bullet", "id": "BUZZO", "pos": {"y": 280, "x": 614}, "weapon": "BAR", "life": 181}, "pos": {"y": 213, "x": 529}, "life": 170}}, {"type": "death", "time_ms": 520550, "round": 1, "round_time_ms": 520550, "data": {"id": "FIGHTA", "attacker": {"means_of_death": "impact", "id": "ZOOMAA", "pos": {"y": 234, "x": 499}, "weapon": "No 74 ST", "life": 182}, "pos": {"y": 237, "x": 556}, "life": 180}}, {"type": "spawn", "time_ms": 521800, "round": 1, "round_time_ms": 521800, "data": {"id": "PRIESTAH", "pos": {"y": 349, "x": 91}, "life": 186}}, {"type": "death", "time_ms": 522050, "round": 1, "round_time_ms": 522050, "data": {"id": "ATTACH", "attacker": {"means_of_death": "pistol_bullet", "id": "SHOCKZ", "pos": {"y": 338, "x": 503}, "weapon": "PPSh-41", "life": 184}, "pos": {"y": 414, "x": 472}, "life": 173}}, {"type": "spawn", "time_ms": 522600, "round": 1, "round_time_ms": 522600, "data": {"id": "FIGHTA", "pos": {"y": 558, "x": 822}, "life": 187}}, {"type": "death", "time_ms": 523150, "round": 1, "round_time_ms": 523150, "data": {"id": "BUZZO", "attacker": {"means_of_death": "pistol_bullet", "id": "ZOOMAA", "pos": {"y": 214, "x": 523}, "weapon": "PPSh-41", "life": 182}, "pos": {"y": 250, "x": 579}, "life": 181}}, {"type": "spawn", "time_ms": 524100, "round": 1, "round_time_ms": 524100, "data": {"id": "ATTACH", "pos": {"y": 344, "x": 173}, "life": 188}}, {"type": "death", "time_ms": 524600, "round": 1, "round_time_ms": 524600, "data": {"id": "DENZ", "attacker": {"means_of_death": "pistol_bullet", "id": "ZOOMAA", "pos": {"y": 219, "x": 551}, "weapon": "PPSh-41", "life": 182}, "pos": {"y": 278, "x": 586}, "life": 183}}, {"type": "spawn", "time_ms": 525200, "round": 1, "round_time_ms": 525200, "data": {"id": "BUZZO", "pos": {"y": 533, "x": 824}, "life": 189}}, {"type": "death", "time_ms": 525650, "round": 1, "round_time_ms": 525650, "data": {"id": "ZOOMAA", "attacker": {"means_of_death": "pistol_bullet", "id": "SHOCKZ", "pos": {"y": 244, "x": 466}, "weapon": "PPSh-41", "life": 184}, "pos": {"y": 226, "x": 519}, "life": 182}}, {"type": "death", "time_ms": 525750, "round": 1, "round_time_ms": 525750, "data": {"id": "SHOCKZ", "attacker": {"means_of_death": "rifle_bullet", "id": "REPLAYS", "pos": {"y": 309, "x": 318}, "weapon": "STG-44", "life": 185}, "pos": {"y": 243, "x": 467}, "life": 184}}, {"type": "spawn", "time_ms": 526650, "round": 1, "round_time_ms": 526650, "data": {"id": "DENZ", "pos": {"y": 444, "x": 816}, "life": 190}}, {"type": "spawn", "time_ms": 527700, "round": 1, "round_time_ms": 527700, "data": {"id": "ZOOMAA", "pos": {"y": 336, "x": 341}, "life": 191}}, {"type": "spawn", "time_ms": 527800, "round": 1, "round_time_ms": 527800, "data": {"id": "SHOCKZ", "pos": {"y": 444, "x": 816}, "life": 192}}, {"type": "roundend", "time_ms": 530750, "round": 1, "round_time_ms": 530750, "data": {"score2": 250, "score1": 121}}]}